{
  "approval_note": null,
  "created_at_utc": "2026-06-30T14:47:49+00:00",
  "decision": {
    "block_cost_usd": 25.0,
    "reason": "Estimated cost $0.379074 is below review threshold $5.0.",
    "review_cost_usd": 5.0,
    "status": "pass"
  },
  "downloaded": [
    {
      "bytes": 1486588,
      "output_path": "D:\\Fogust\\Workspace\\Investment\\Project\\SPY 0DTE - Higanbana\\data\\raw\\spy_0dte\\databento\\oos_2024_03_intraday_exit_30m_chunk1\\2024-03-01_entry_a_0935.dbn.zst",
      "sha256": "e27db6c49c72d801882785112cf0bea00bac70e18ef7132373813028e361ade4",
      "source": "downloaded",
      "window": "2024-03-01_entry_a_0935"
    },
    {
      "bytes": 1791301,
      "output_path": "D:\\Fogust\\Workspace\\Investment\\Project\\SPY 0DTE - Higanbana\\data\\raw\\spy_0dte\\databento\\oos_2024_03_intraday_exit_30m_chunk1\\2024-03-01_entry_b_1000.dbn.zst",
      "sha256": "2bb8751dc14d248435d448d5bd7a3f79b122066f07acece3253d5ad1ac42d4d3",
      "source": "downloaded",
      "window": "2024-03-01_entry_b_1000"
    },
    {
      "bytes": 1908910,
      "output_path": "D:\\Fogust\\Workspace\\Investment\\Project\\SPY 0DTE - Higanbana\\data\\raw\\spy_0dte\\databento\\oos_2024_03_intraday_exit_30m_chunk1\\2024-03-01_exit_check_1030.dbn.zst",
      "sha256": "05e977c997b1975cd6d7c416bdc5e9096d66e901fdaadb9bc426b30ae7b55120",
      "source": "downloaded",
      "window": "2024-03-01_exit_check_1030"
    },
    {
      "bytes": 1953556,
      "output_path": "D:\\Fogust\\Workspace\\Investment\\Project\\SPY 0DTE - Higanbana\\data\\raw\\spy_0dte\\databento\\oos_2024_03_intraday_exit_30m_chunk1\\2024-03-01_exit_check_1100.dbn.zst",
      "sha256": "3bd595c5364e422d3962eea2c390a6ccdd562b7475c27aa67ead878728b2fa6c",
      "source": "downloaded",
      "window": "2024-03-01_exit_check_1100"
    },
    {
      "bytes": 2004351,
      "output_path": "D:\\Fogust\\Workspace\\Investment\\Project\\SPY 0DTE - Higanbana\\data\\raw\\spy_0dte\\databento\\oos_2024_03_intraday_exit_30m_chunk1\\2024-03-01_exit_check_1130.dbn.zst",
      "sha256": "f913efb895079b57ec1e59d0f89a0c0a0691ba1484af56a8823e14bf1bfd457a",
      "source": "downloaded",
      "window": "2024-03-01_exit_check_1130"
    },
    {
      "bytes": 2040197,
      "output_path": "D:\\Fogust\\Workspace\\Investment\\Project\\SPY 0DTE - Higanbana\\data\\raw\\spy_0dte\\databento\\oos_2024_03_intraday_exit_30m_chunk1\\2024-03-01_exit_check_1200.dbn.zst",
      "sha256": "782d53a1c9ab01bdc04fa9eb18f50d0ff53c49329e1c4faa0d1e543b8ca64c8c",
      "source": "downloaded",
      "window": "2024-03-01_exit_check_1200"
    },
    {
      "bytes": 2062839,
      "output_path": "D:\\Fogust\\Workspace\\Investment\\Project\\SPY 0DTE - Higanbana\\data\\raw\\spy_0dte\\databento\\oos_2024_03_intraday_exit_30m_chunk1\\2024-03-01_exit_check_1230.dbn.zst",
      "sha256": "97f9e034267a4fd69d2ec2db21d990a0d448355acf1753323ca511ad40969eef",
      "source": "downloaded",
      "window": "2024-03-01_exit_check_1230"
    },
    {
      "bytes": 2092013,
      "output_path": "D:\\Fogust\\Workspace\\Investment\\Project\\SPY 0DTE - Higanbana\\data\\raw\\spy_0dte\\databento\\oos_2024_03_intraday_exit_30m_chunk1\\2024-03-01_exit_check_1300.dbn.zst",
      "sha256": "57f99c007950fbb5f3bccdf171f766c63413a1f333676e9e9baadec305ccddaa",
      "source": "downloaded",
      "window": "2024-03-01_exit_check_1300"
    },
    {
      "bytes": 2117124,
      "output_path": "D:\\Fogust\\Workspace\\Investment\\Project\\SPY 0DTE - Higanbana\\data\\raw\\spy_0dte\\databento\\oos_2024_03_intraday_exit_30m_chunk1\\2024-03-01_exit_check_1330.dbn.zst",
      "sha256": "63a9d6b7257685208effa8edd327d22164e10c693607e64d97b06767c0331597",
      "source": "downloaded",
      "window": "2024-03-01_exit_check_1330"
    },
    {
      "bytes": 2129158,
      "output_path": "D:\\Fogust\\Workspace\\Investment\\Project\\SPY 0DTE - Higanbana\\data\\raw\\spy_0dte\\databento\\oos_2024_03_intraday_exit_30m_chunk1\\2024-03-01_exit_check_1400.dbn.zst",
      "sha256": "496886c5f8a0f2e47f122d513aa82337a1ffb3ae9b9d249843567a94ceb6636b",
      "source": "downloaded",
      "window": "2024-03-01_exit_check_1400"
    },
    {
      "bytes": 2158102,
      "output_path": "D:\\Fogust\\Workspace\\Investment\\Project\\SPY 0DTE - Higanbana\\data\\raw\\spy_0dte\\databento\\oos_2024_03_intraday_exit_30m_chunk1\\2024-03-01_exit_check_1430.dbn.zst",
      "sha256": "abde512e7f727a0b031d83bdcba6062acbb686196c25326d97edee8319b01538",
      "source": "downloaded",
      "window": "2024-03-01_exit_check_1430"
    },
    {
      "bytes": 2176430,
      "output_path": "D:\\Fogust\\Workspace\\Investment\\Project\\SPY 0DTE - Higanbana\\data\\raw\\spy_0dte\\databento\\oos_2024_03_intraday_exit_30m_chunk1\\2024-03-01_exit_check_1500.dbn.zst",
      "sha256": "2b02313ed013335c5fe8bea80ed98a7c512dd86a73e96f2a42036e3087418571",
      "source": "downloaded",
      "window": "2024-03-01_exit_check_1500"
    },
    {
      "bytes": 2185461,
      "output_path": "D:\\Fogust\\Workspace\\Investment\\Project\\SPY 0DTE - Higanbana\\data\\raw\\spy_0dte\\databento\\oos_2024_03_intraday_exit_30m_chunk1\\2024-03-01_exit_check_1530.dbn.zst",
      "sha256": "319e7fdbe26a6fe5e5be1acaf1e68358aafb58cb99f7096159e902a5960cd4d9",
      "source": "downloaded",
      "window": "2024-03-01_exit_check_1530"
    },
    {
      "bytes": 2182297,
      "output_path": "D:\\Fogust\\Workspace\\Investment\\Project\\SPY 0DTE - Higanbana\\data\\raw\\spy_0dte\\databento\\oos_2024_03_intraday_exit_30m_chunk1\\2024-03-01_forced_close_1545.dbn.zst",
      "sha256": "37ef4c64413a2fe6a4f7cf1d97a0271676efefc208b845dcfabb8f13cd69b560",
      "source": "downloaded",
      "window": "2024-03-01_forced_close_1545"
    }
  ],
  "items": [
    {
      "dataset": "OPRA.PILLAR",
      "end": "2024-03-01T14:40:00+00:00",
      "estimated_cost_usd": 0.025815069675,
      "output_path": "D:\\Fogust\\Workspace\\Investment\\Project\\SPY 0DTE - Higanbana\\data\\raw\\spy_0dte\\databento\\oos_2024_03_intraday_exit_30m_chunk1\\2024-03-01_entry_a_0935.dbn.zst",
      "schema": "cbbo-1m",
      "start": "2024-03-01T14:30:00+00:00",
      "stype_in": "parent",
      "symbols": [
        "SPY.OPT"
      ],
      "window": "2024-03-01_entry_a_0935"
    },
    {
      "dataset": "OPRA.PILLAR",
      "end": "2024-03-01T15:05:00+00:00",
      "estimated_cost_usd": 0.027173757553,
      "output_path": "D:\\Fogust\\Workspace\\Investment\\Project\\SPY 0DTE - Higanbana\\data\\raw\\spy_0dte\\databento\\oos_2024_03_intraday_exit_30m_chunk1\\2024-03-01_entry_b_1000.dbn.zst",
      "schema": "cbbo-1m",
      "start": "2024-03-01T14:55:00+00:00",
      "stype_in": "parent",
      "symbols": [
        "SPY.OPT"
      ],
      "window": "2024-03-01_entry_b_1000"
    },
    {
      "dataset": "OPRA.PILLAR",
      "end": "2024-03-01T15:35:00+00:00",
      "estimated_cost_usd": 0.027173757553,
      "output_path": "D:\\Fogust\\Workspace\\Investment\\Project\\SPY 0DTE - Higanbana\\data\\raw\\spy_0dte\\databento\\oos_2024_03_intraday_exit_30m_chunk1\\2024-03-01_exit_check_1030.dbn.zst",
      "schema": "cbbo-1m",
      "start": "2024-03-01T15:25:00+00:00",
      "stype_in": "parent",
      "symbols": [
        "SPY.OPT"
      ],
      "window": "2024-03-01_exit_check_1030"
    },
    {
      "dataset": "OPRA.PILLAR",
      "end": "2024-03-01T16:05:00+00:00",
      "estimated_cost_usd": 0.027173757553,
      "output_path": "D:\\Fogust\\Workspace\\Investment\\Project\\SPY 0DTE - Higanbana\\data\\raw\\spy_0dte\\databento\\oos_2024_03_intraday_exit_30m_chunk1\\2024-03-01_exit_check_1100.dbn.zst",
      "schema": "cbbo-1m",
      "start": "2024-03-01T15:55:00+00:00",
      "stype_in": "parent",
      "symbols": [
        "SPY.OPT"
      ],
      "window": "2024-03-01_exit_check_1100"
    },
    {
      "dataset": "OPRA.PILLAR",
      "end": "2024-03-01T16:35:00+00:00",
      "estimated_cost_usd": 0.027173757553,
      "output_path": "D:\\Fogust\\Workspace\\Investment\\Project\\SPY 0DTE - Higanbana\\data\\raw\\spy_0dte\\databento\\oos_2024_03_intraday_exit_30m_chunk1\\2024-03-01_exit_check_1130.dbn.zst",
      "schema": "cbbo-1m",
      "start": "2024-03-01T16:25:00+00:00",
      "stype_in": "parent",
      "symbols": [
        "SPY.OPT"
      ],
      "window": "2024-03-01_exit_check_1130"
    },
    {
      "dataset": "OPRA.PILLAR",
      "end": "2024-03-01T17:05:00+00:00",
      "estimated_cost_usd": 0.027173757553,
      "output_path": "D:\\Fogust\\Workspace\\Investment\\Project\\SPY 0DTE - Higanbana\\data\\raw\\spy_0dte\\databento\\oos_2024_03_intraday_exit_30m_chunk1\\2024-03-01_exit_check_1200.dbn.zst",
      "schema": "cbbo-1m",
      "start": "2024-03-01T16:55:00+00:00",
      "stype_in": "parent",
      "symbols": [
        "SPY.OPT"
      ],
      "window": "2024-03-01_exit_check_1200"
    },
    {
      "dataset": "OPRA.PILLAR",
      "end": "2024-03-01T17:35:00+00:00",
      "estimated_cost_usd": 0.027173757553,
      "output_path": "D:\\Fogust\\Workspace\\Investment\\Project\\SPY 0DTE - Higanbana\\data\\raw\\spy_0dte\\databento\\oos_2024_03_intraday_exit_30m_chunk1\\2024-03-01_exit_check_1230.dbn.zst",
      "schema": "cbbo-1m",
      "start": "2024-03-01T17:25:00+00:00",
      "stype_in": "parent",
      "symbols": [
        "SPY.OPT"
      ],
      "window": "2024-03-01_exit_check_1230"
    },
    {
      "dataset": "OPRA.PILLAR",
      "end": "2024-03-01T18:05:00+00:00",
      "estimated_cost_usd": 0.027173757553,
      "output_path": "D:\\Fogust\\Workspace\\Investment\\Project\\SPY 0DTE - Higanbana\\data\\raw\\spy_0dte\\databento\\oos_2024_03_intraday_exit_30m_chunk1\\2024-03-01_exit_check_1300.dbn.zst",
      "schema": "cbbo-1m",
      "start": "2024-03-01T17:55:00+00:00",
      "stype_in": "parent",
      "symbols": [
        "SPY.OPT"
      ],
      "window": "2024-03-01_exit_check_1300"
    },
    {
      "dataset": "OPRA.PILLAR",
      "end": "2024-03-01T18:35:00+00:00",
      "estimated_cost_usd": 0.027173757553,
      "output_path": "D:\\Fogust\\Workspace\\Investment\\Project\\SPY 0DTE - Higanbana\\data\\raw\\spy_0dte\\databento\\oos_2024_03_intraday_exit_30m_chunk1\\2024-03-01_exit_check_1330.dbn.zst",
      "schema": "cbbo-1m",
      "start": "2024-03-01T18:25:00+00:00",
      "stype_in": "parent",
      "symbols": [
        "SPY.OPT"
      ],
      "window": "2024-03-01_exit_check_1330"
    },
    {
      "dataset": "OPRA.PILLAR",
      "end": "2024-03-01T19:05:00+00:00",
      "estimated_cost_usd": 0.027173757553,
      "output_path": "D:\\Fogust\\Workspace\\Investment\\Project\\SPY 0DTE - Higanbana\\data\\raw\\spy_0dte\\databento\\oos_2024_03_intraday_exit_30m_chunk1\\2024-03-01_exit_check_1400.dbn.zst",
      "schema": "cbbo-1m",
      "start": "2024-03-01T18:55:00+00:00",
      "stype_in": "parent",
      "symbols": [
        "SPY.OPT"
      ],
      "window": "2024-03-01_exit_check_1400"
    },
    {
      "dataset": "OPRA.PILLAR",
      "end": "2024-03-01T19:35:00+00:00",
      "estimated_cost_usd": 0.027173757553,
      "output_path": "D:\\Fogust\\Workspace\\Investment\\Project\\SPY 0DTE - Higanbana\\data\\raw\\spy_0dte\\databento\\oos_2024_03_intraday_exit_30m_chunk1\\2024-03-01_exit_check_1430.dbn.zst",
      "schema": "cbbo-1m",
      "start": "2024-03-01T19:25:00+00:00",
      "stype_in": "parent",
      "symbols": [
        "SPY.OPT"
      ],
      "window": "2024-03-01_exit_check_1430"
    },
    {
      "dataset": "OPRA.PILLAR",
      "end": "2024-03-01T20:05:00+00:00",
      "estimated_cost_usd": 0.027173757553,
      "output_path": "D:\\Fogust\\Workspace\\Investment\\Project\\SPY 0DTE - Higanbana\\data\\raw\\spy_0dte\\databento\\oos_2024_03_intraday_exit_30m_chunk1\\2024-03-01_exit_check_1500.dbn.zst",
      "schema": "cbbo-1m",
      "start": "2024-03-01T19:55:00+00:00",
      "stype_in": "parent",
      "symbols": [
        "SPY.OPT"
      ],
      "window": "2024-03-01_exit_check_1500"
    },
    {
      "dataset": "OPRA.PILLAR",
      "end": "2024-03-01T20:35:00+00:00",
      "estimated_cost_usd": 0.027173757553,
      "output_path": "D:\\Fogust\\Workspace\\Investment\\Project\\SPY 0DTE - Higanbana\\data\\raw\\spy_0dte\\databento\\oos_2024_03_intraday_exit_30m_chunk1\\2024-03-01_exit_check_1530.dbn.zst",
      "schema": "cbbo-1m",
      "start": "2024-03-01T20:25:00+00:00",
      "stype_in": "parent",
      "symbols": [
        "SPY.OPT"
      ],
      "window": "2024-03-01_exit_check_1530"
    },
    {
      "dataset": "OPRA.PILLAR",
      "end": "2024-03-01T20:50:00+00:00",
      "estimated_cost_usd": 0.027173757553,
      "output_path": "D:\\Fogust\\Workspace\\Investment\\Project\\SPY 0DTE - Higanbana\\data\\raw\\spy_0dte\\databento\\oos_2024_03_intraday_exit_30m_chunk1\\2024-03-01_forced_close_1545.dbn.zst",
      "schema": "cbbo-1m",
      "start": "2024-03-01T20:40:00+00:00",
      "stype_in": "parent",
      "symbols": [
        "SPY.OPT"
      ],
      "window": "2024-03-01_forced_close_1545"
    }
  ],
  "mode": "download_complete",
  "request_count": 14,
  "scenario": "oos_2024_03_intraday_exit_30m_chunk1",
  "source_cost_report": "reports\\data_cost\\databento_cost_oos_2024_03_intraday_exit_30m_chunk1.json",
  "total_estimated_cost_usd": 0.379074
}