{
  "coverage_end": "2023-07-31",
  "coverage_start": "2023-07-03",
  "file_count": 280,
  "files": [
    {
      "file": "data\\raw\\spy_0dte\\databento\\insample_2023_07\\insample_2023_07\\2023-07-03_entry_a_0935.dbn.zst",
      "input_rows": 70182,
      "output_rows": 2394,
      "skipped_invalid_quote": 0,
      "skipped_non_0dte": 67788,
      "trade_date": "2023-07-03"
    },
    {
      "file": "data\\raw\\spy_0dte\\databento\\insample_2023_07\\insample_2023_07\\2023-07-03_entry_b_1000.dbn.zst",
      "input_rows": 77980,
      "output_rows": 2660,
      "skipped_invalid_quote": 0,
      "skipped_non_0dte": 75320,
      "trade_date": "2023-07-03"
    },
    {
      "file": "data\\raw\\spy_0dte\\databento\\insample_2023_07\\insample_2023_07\\2023-07-03_exit_check_1030.dbn.zst",
      "input_rows": 77980,
      "output_rows": 2660,
      "skipped_invalid_quote": 0,
      "skipped_non_0dte": 75320,
      "trade_date": "2023-07-03"
    },
    {
      "file": "data\\raw\\spy_0dte\\databento\\insample_2023_07\\insample_2023_07\\2023-07-03_exit_check_1100.dbn.zst",
      "input_rows": 77980,
      "output_rows": 2660,
      "skipped_invalid_quote": 0,
      "skipped_non_0dte": 75320,
      "trade_date": "2023-07-03"
    },
    {
      "file": "data\\raw\\spy_0dte\\databento\\insample_2023_07\\insample_2023_07\\2023-07-03_exit_check_1130.dbn.zst",
      "input_rows": 77980,
      "output_rows": 2660,
      "skipped_invalid_quote": 0,
      "skipped_non_0dte": 75320,
      "trade_date": "2023-07-03"
    },
    {
      "file": "data\\raw\\spy_0dte\\databento\\insample_2023_07\\insample_2023_07\\2023-07-03_exit_check_1200.dbn.zst",
      "input_rows": 77980,
      "output_rows": 2660,
      "skipped_invalid_quote": 0,
      "skipped_non_0dte": 75320,
      "trade_date": "2023-07-03"
    },
    {
      "file": "data\\raw\\spy_0dte\\databento\\insample_2023_07\\insample_2023_07\\2023-07-03_exit_check_1230.dbn.zst",
      "input_rows": 77980,
      "output_rows": 2660,
      "skipped_invalid_quote": 0,
      "skipped_non_0dte": 75320,
      "trade_date": "2023-07-03"
    },
    {
      "file": "data\\raw\\spy_0dte\\databento\\insample_2023_07\\insample_2023_07\\2023-07-03_exit_check_1300.dbn.zst",
      "input_rows": 77980,
      "output_rows": 2660,
      "skipped_invalid_quote": 0,
      "skipped_non_0dte": 75320,
      "trade_date": "2023-07-03"
    },
    {
      "file": "data\\raw\\spy_0dte\\databento\\insample_2023_07\\insample_2023_07\\2023-07-03_exit_check_1330.dbn.zst",
      "input_rows": 0,
      "output_rows": 0,
      "skipped_invalid_quote": 0,
      "skipped_non_0dte": 0,
      "trade_date": "2023-07-03"
    },
    {
      "file": "data\\raw\\spy_0dte\\databento\\insample_2023_07\\insample_2023_07\\2023-07-03_exit_check_1400.dbn.zst",
      "input_rows": 0,
      "output_rows": 0,
      "skipped_invalid_quote": 0,
      "skipped_non_0dte": 0,
      "trade_date": "2023-07-03"
    },
    {
      "file": "data\\raw\\spy_0dte\\databento\\insample_2023_07\\insample_2023_07\\2023-07-03_exit_check_1430.dbn.zst",
      "input_rows": 0,
      "output_rows": 0,
      "skipped_invalid_quote": 0,
      "skipped_non_0dte": 0,
      "trade_date": "2023-07-03"
    },
    {
      "file": "data\\raw\\spy_0dte\\databento\\insample_2023_07\\insample_2023_07\\2023-07-03_exit_check_1500.dbn.zst",
      "input_rows": 0,
      "output_rows": 0,
      "skipped_invalid_quote": 0,
      "skipped_non_0dte": 0,
      "trade_date": "2023-07-03"
    },
    {
      "file": "data\\raw\\spy_0dte\\databento\\insample_2023_07\\insample_2023_07\\2023-07-03_exit_check_1530.dbn.zst",
      "input_rows": 0,
      "output_rows": 0,
      "skipped_invalid_quote": 0,
      "skipped_non_0dte": 0,
      "trade_date": "2023-07-03"
    },
    {
      "file": "data\\raw\\spy_0dte\\databento\\insample_2023_07\\insample_2023_07\\2023-07-03_forced_close_1545.dbn.zst",
      "input_rows": 0,
      "output_rows": 0,
      "skipped_invalid_quote": 0,
      "skipped_non_0dte": 0,
      "trade_date": "2023-07-03"
    },
    {
      "file": "data\\raw\\spy_0dte\\databento\\insample_2023_07\\insample_2023_07\\2023-07-05_entry_a_0935.dbn.zst",
      "input_rows": 68994,
      "output_rows": 2273,
      "skipped_invalid_quote": 121,
      "skipped_non_0dte": 66600,
      "trade_date": "2023-07-05"
    },
    {
      "file": "data\\raw\\spy_0dte\\databento\\insample_2023_07\\insample_2023_07\\2023-07-05_entry_b_1000.dbn.zst",
      "input_rows": 76660,
      "output_rows": 2660,
      "skipped_invalid_quote": 0,
      "skipped_non_0dte": 74000,
      "trade_date": "2023-07-05"
    },
    {
      "file": "data\\raw\\spy_0dte\\databento\\insample_2023_07\\insample_2023_07\\2023-07-05_exit_check_1030.dbn.zst",
      "input_rows": 76660,
      "output_rows": 2660,
      "skipped_invalid_quote": 0,
      "skipped_non_0dte": 74000,
      "trade_date": "2023-07-05"
    },
    {
      "file": "data\\raw\\spy_0dte\\databento\\insample_2023_07\\insample_2023_07\\2023-07-05_exit_check_1100.dbn.zst",
      "input_rows": 76660,
      "output_rows": 2660,
      "skipped_invalid_quote": 0,
      "skipped_non_0dte": 74000,
      "trade_date": "2023-07-05"
    },
    {
      "file": "data\\raw\\spy_0dte\\databento\\insample_2023_07\\insample_2023_07\\2023-07-05_exit_check_1130.dbn.zst",
      "input_rows": 76660,
      "output_rows": 2660,
      "skipped_invalid_quote": 0,
      "skipped_non_0dte": 74000,
      "trade_date": "2023-07-05"
    },
    {
      "file": "data\\raw\\spy_0dte\\databento\\insample_2023_07\\insample_2023_07\\2023-07-05_exit_check_1200.dbn.zst",
      "input_rows": 76660,
      "output_rows": 2660,
      "skipped_invalid_quote": 0,
      "skipped_non_0dte": 74000,
      "trade_date": "2023-07-05"
    },
    {
      "file": "data\\raw\\spy_0dte\\databento\\insample_2023_07\\insample_2023_07\\2023-07-05_exit_check_1230.dbn.zst",
      "input_rows": 76660,
      "output_rows": 2660,
      "skipped_invalid_quote": 0,
      "skipped_non_0dte": 74000,
      "trade_date": "2023-07-05"
    },
    {
      "file": "data\\raw\\spy_0dte\\databento\\insample_2023_07\\insample_2023_07\\2023-07-05_exit_check_1300.dbn.zst",
      "input_rows": 76660,
      "output_rows": 2660,
      "skipped_invalid_quote": 0,
      "skipped_non_0dte": 74000,
      "trade_date": "2023-07-05"
    },
    {
      "file": "data\\raw\\spy_0dte\\databento\\insample_2023_07\\insample_2023_07\\2023-07-05_exit_check_1330.dbn.zst",
      "input_rows": 76660,
      "output_rows": 2660,
      "skipped_invalid_quote": 0,
      "skipped_non_0dte": 74000,
      "trade_date": "2023-07-05"
    },
    {
      "file": "data\\raw\\spy_0dte\\databento\\insample_2023_07\\insample_2023_07\\2023-07-05_exit_check_1400.dbn.zst",
      "input_rows": 76660,
      "output_rows": 2660,
      "skipped_invalid_quote": 0,
      "skipped_non_0dte": 74000,
      "trade_date": "2023-07-05"
    },
    {
      "file": "data\\raw\\spy_0dte\\databento\\insample_2023_07\\insample_2023_07\\2023-07-05_exit_check_1430.dbn.zst",
      "input_rows": 76660,
      "output_rows": 2660,
      "skipped_invalid_quote": 0,
      "skipped_non_0dte": 74000,
      "trade_date": "2023-07-05"
    },
    {
      "file": "data\\raw\\spy_0dte\\databento\\insample_2023_07\\insample_2023_07\\2023-07-05_exit_check_1500.dbn.zst",
      "input_rows": 76660,
      "output_rows": 2660,
      "skipped_invalid_quote": 0,
      "skipped_non_0dte": 74000,
      "trade_date": "2023-07-05"
    },
    {
      "file": "data\\raw\\spy_0dte\\databento\\insample_2023_07\\insample_2023_07\\2023-07-05_exit_check_1530.dbn.zst",
      "input_rows": 76660,
      "output_rows": 2660,
      "skipped_invalid_quote": 0,
      "skipped_non_0dte": 74000,
      "trade_date": "2023-07-05"
    },
    {
      "file": "data\\raw\\spy_0dte\\databento\\insample_2023_07\\insample_2023_07\\2023-07-05_forced_close_1545.dbn.zst",
      "input_rows": 76660,
      "output_rows": 2660,
      "skipped_invalid_quote": 0,
      "skipped_non_0dte": 74000,
      "trade_date": "2023-07-05"
    },
    {
      "file": "data\\raw\\spy_0dte\\databento\\insample_2023_07\\insample_2023_07\\2023-07-06_entry_a_0935.dbn.zst",
      "input_rows": 73044,
      "output_rows": 2394,
      "skipped_invalid_quote": 0,
      "skipped_non_0dte": 70650,
      "trade_date": "2023-07-06"
    },
    {
      "file": "data\\raw\\spy_0dte\\databento\\insample_2023_07\\insample_2023_07\\2023-07-06_entry_b_1000.dbn.zst",
      "input_rows": 81160,
      "output_rows": 2660,
      "skipped_invalid_quote": 0,
      "skipped_non_0dte": 78500,
      "trade_date": "2023-07-06"
    },
    {
      "file": "data\\raw\\spy_0dte\\databento\\insample_2023_07\\insample_2023_07\\2023-07-06_exit_check_1030.dbn.zst",
      "input_rows": 81160,
      "output_rows": 2660,
      "skipped_invalid_quote": 0,
      "skipped_non_0dte": 78500,
      "trade_date": "2023-07-06"
    },
    {
      "file": "data\\raw\\spy_0dte\\databento\\insample_2023_07\\insample_2023_07\\2023-07-06_exit_check_1100.dbn.zst",
      "input_rows": 81160,
      "output_rows": 2660,
      "skipped_invalid_quote": 0,
      "skipped_non_0dte": 78500,
      "trade_date": "2023-07-06"
    },
    {
      "file": "data\\raw\\spy_0dte\\databento\\insample_2023_07\\insample_2023_07\\2023-07-06_exit_check_1130.dbn.zst",
      "input_rows": 81160,
      "output_rows": 2660,
      "skipped_invalid_quote": 0,
      "skipped_non_0dte": 78500,
      "trade_date": "2023-07-06"
    },
    {
      "file": "data\\raw\\spy_0dte\\databento\\insample_2023_07\\insample_2023_07\\2023-07-06_exit_check_1200.dbn.zst",
      "input_rows": 81160,
      "output_rows": 2660,
      "skipped_invalid_quote": 0,
      "skipped_non_0dte": 78500,
      "trade_date": "2023-07-06"
    },
    {
      "file": "data\\raw\\spy_0dte\\databento\\insample_2023_07\\insample_2023_07\\2023-07-06_exit_check_1230.dbn.zst",
      "input_rows": 81160,
      "output_rows": 2660,
      "skipped_invalid_quote": 0,
      "skipped_non_0dte": 78500,
      "trade_date": "2023-07-06"
    },
    {
      "file": "data\\raw\\spy_0dte\\databento\\insample_2023_07\\insample_2023_07\\2023-07-06_exit_check_1300.dbn.zst",
      "input_rows": 81160,
      "output_rows": 2660,
      "skipped_invalid_quote": 0,
      "skipped_non_0dte": 78500,
      "trade_date": "2023-07-06"
    },
    {
      "file": "data\\raw\\spy_0dte\\databento\\insample_2023_07\\insample_2023_07\\2023-07-06_exit_check_1330.dbn.zst",
      "input_rows": 81160,
      "output_rows": 2660,
      "skipped_invalid_quote": 0,
      "skipped_non_0dte": 78500,
      "trade_date": "2023-07-06"
    },
    {
      "file": "data\\raw\\spy_0dte\\databento\\insample_2023_07\\insample_2023_07\\2023-07-06_exit_check_1400.dbn.zst",
      "input_rows": 81160,
      "output_rows": 2660,
      "skipped_invalid_quote": 0,
      "skipped_non_0dte": 78500,
      "trade_date": "2023-07-06"
    },
    {
      "file": "data\\raw\\spy_0dte\\databento\\insample_2023_07\\insample_2023_07\\2023-07-06_exit_check_1430.dbn.zst",
      "input_rows": 81160,
      "output_rows": 2660,
      "skipped_invalid_quote": 0,
      "skipped_non_0dte": 78500,
      "trade_date": "2023-07-06"
    },
    {
      "file": "data\\raw\\spy_0dte\\databento\\insample_2023_07\\insample_2023_07\\2023-07-06_exit_check_1500.dbn.zst",
      "input_rows": 81160,
      "output_rows": 2660,
      "skipped_invalid_quote": 0,
      "skipped_non_0dte": 78500,
      "trade_date": "2023-07-06"
    },
    {
      "file": "data\\raw\\spy_0dte\\databento\\insample_2023_07\\insample_2023_07\\2023-07-06_exit_check_1530.dbn.zst",
      "input_rows": 81160,
      "output_rows": 2660,
      "skipped_invalid_quote": 0,
      "skipped_non_0dte": 78500,
      "trade_date": "2023-07-06"
    },
    {
      "file": "data\\raw\\spy_0dte\\databento\\insample_2023_07\\insample_2023_07\\2023-07-06_forced_close_1545.dbn.zst",
      "input_rows": 81160,
      "output_rows": 2660,
      "skipped_invalid_quote": 0,
      "skipped_non_0dte": 78500,
      "trade_date": "2023-07-06"
    },
    {
      "file": "data\\raw\\spy_0dte\\databento\\insample_2023_07\\insample_2023_07\\2023-07-07_entry_a_0935.dbn.zst",
      "input_rows": 71820,
      "output_rows": 2754,
      "skipped_invalid_quote": 0,
      "skipped_non_0dte": 69066,
      "trade_date": "2023-07-07"
    },
    {
      "file": "data\\raw\\spy_0dte\\databento\\insample_2023_07\\insample_2023_07\\2023-07-07_entry_b_1000.dbn.zst",
      "input_rows": 79800,
      "output_rows": 3060,
      "skipped_invalid_quote": 0,
      "skipped_non_0dte": 76740,
      "trade_date": "2023-07-07"
    },
    {
      "file": "data\\raw\\spy_0dte\\databento\\insample_2023_07\\insample_2023_07\\2023-07-07_exit_check_1030.dbn.zst",
      "input_rows": 79800,
      "output_rows": 3060,
      "skipped_invalid_quote": 0,
      "skipped_non_0dte": 76740,
      "trade_date": "2023-07-07"
    },
    {
      "file": "data\\raw\\spy_0dte\\databento\\insample_2023_07\\insample_2023_07\\2023-07-07_exit_check_1100.dbn.zst",
      "input_rows": 79800,
      "output_rows": 3060,
      "skipped_invalid_quote": 0,
      "skipped_non_0dte": 76740,
      "trade_date": "2023-07-07"
    },
    {
      "file": "data\\raw\\spy_0dte\\databento\\insample_2023_07\\insample_2023_07\\2023-07-07_exit_check_1130.dbn.zst",
      "input_rows": 79800,
      "output_rows": 3060,
      "skipped_invalid_quote": 0,
      "skipped_non_0dte": 76740,
      "trade_date": "2023-07-07"
    },
    {
      "file": "data\\raw\\spy_0dte\\databento\\insample_2023_07\\insample_2023_07\\2023-07-07_exit_check_1200.dbn.zst",
      "input_rows": 79800,
      "output_rows": 3060,
      "skipped_invalid_quote": 0,
      "skipped_non_0dte": 76740,
      "trade_date": "2023-07-07"
    },
    {
      "file": "data\\raw\\spy_0dte\\databento\\insample_2023_07\\insample_2023_07\\2023-07-07_exit_check_1230.dbn.zst",
      "input_rows": 79800,
      "output_rows": 3060,
      "skipped_invalid_quote": 0,
      "skipped_non_0dte": 76740,
      "trade_date": "2023-07-07"
    },
    {
      "file": "data\\raw\\spy_0dte\\databento\\insample_2023_07\\insample_2023_07\\2023-07-07_exit_check_1300.dbn.zst",
      "input_rows": 79800,
      "output_rows": 3060,
      "skipped_invalid_quote": 0,
      "skipped_non_0dte": 76740,
      "trade_date": "2023-07-07"
    },
    {
      "file": "data\\raw\\spy_0dte\\databento\\insample_2023_07\\insample_2023_07\\2023-07-07_exit_check_1330.dbn.zst",
      "input_rows": 79800,
      "output_rows": 3060,
      "skipped_invalid_quote": 0,
      "skipped_non_0dte": 76740,
      "trade_date": "2023-07-07"
    },
    {
      "file": "data\\raw\\spy_0dte\\databento\\insample_2023_07\\insample_2023_07\\2023-07-07_exit_check_1400.dbn.zst",
      "input_rows": 79800,
      "output_rows": 3060,
      "skipped_invalid_quote": 0,
      "skipped_non_0dte": 76740,
      "trade_date": "2023-07-07"
    },
    {
      "file": "data\\raw\\spy_0dte\\databento\\insample_2023_07\\insample_2023_07\\2023-07-07_exit_check_1430.dbn.zst",
      "input_rows": 79800,
      "output_rows": 3060,
      "skipped_invalid_quote": 0,
      "skipped_non_0dte": 76740,
      "trade_date": "2023-07-07"
    },
    {
      "file": "data\\raw\\spy_0dte\\databento\\insample_2023_07\\insample_2023_07\\2023-07-07_exit_check_1500.dbn.zst",
      "input_rows": 79800,
      "output_rows": 3060,
      "skipped_invalid_quote": 0,
      "skipped_non_0dte": 76740,
      "trade_date": "2023-07-07"
    },
    {
      "file": "data\\raw\\spy_0dte\\databento\\insample_2023_07\\insample_2023_07\\2023-07-07_exit_check_1530.dbn.zst",
      "input_rows": 79800,
      "output_rows": 3060,
      "skipped_invalid_quote": 0,
      "skipped_non_0dte": 76740,
      "trade_date": "2023-07-07"
    },
    {
      "file": "data\\raw\\spy_0dte\\databento\\insample_2023_07\\insample_2023_07\\2023-07-07_forced_close_1545.dbn.zst",
      "input_rows": 79800,
      "output_rows": 3060,
      "skipped_invalid_quote": 0,
      "skipped_non_0dte": 76740,
      "trade_date": "2023-07-07"
    },
    {
      "file": "data\\raw\\spy_0dte\\databento\\insample_2023_07\\insample_2023_07\\2023-07-10_entry_a_0935.dbn.zst",
      "input_rows": 69786,
      "output_rows": 2358,
      "skipped_invalid_quote": 0,
      "skipped_non_0dte": 67428,
      "trade_date": "2023-07-10"
    },
    {
      "file": "data\\raw\\spy_0dte\\databento\\insample_2023_07\\insample_2023_07\\2023-07-10_entry_b_1000.dbn.zst",
      "input_rows": 77540,
      "output_rows": 2620,
      "skipped_invalid_quote": 0,
      "skipped_non_0dte": 74920,
      "trade_date": "2023-07-10"
    },
    {
      "file": "data\\raw\\spy_0dte\\databento\\insample_2023_07\\insample_2023_07\\2023-07-10_exit_check_1030.dbn.zst",
      "input_rows": 77540,
      "output_rows": 2620,
      "skipped_invalid_quote": 0,
      "skipped_non_0dte": 74920,
      "trade_date": "2023-07-10"
    },
    {
      "file": "data\\raw\\spy_0dte\\databento\\insample_2023_07\\insample_2023_07\\2023-07-10_exit_check_1100.dbn.zst",
      "input_rows": 77540,
      "output_rows": 2620,
      "skipped_invalid_quote": 0,
      "skipped_non_0dte": 74920,
      "trade_date": "2023-07-10"
    },
    {
      "file": "data\\raw\\spy_0dte\\databento\\insample_2023_07\\insample_2023_07\\2023-07-10_exit_check_1130.dbn.zst",
      "input_rows": 77540,
      "output_rows": 2620,
      "skipped_invalid_quote": 0,
      "skipped_non_0dte": 74920,
      "trade_date": "2023-07-10"
    },
    {
      "file": "data\\raw\\spy_0dte\\databento\\insample_2023_07\\insample_2023_07\\2023-07-10_exit_check_1200.dbn.zst",
      "input_rows": 77540,
      "output_rows": 2620,
      "skipped_invalid_quote": 0,
      "skipped_non_0dte": 74920,
      "trade_date": "2023-07-10"
    },
    {
      "file": "data\\raw\\spy_0dte\\databento\\insample_2023_07\\insample_2023_07\\2023-07-10_exit_check_1230.dbn.zst",
      "input_rows": 77540,
      "output_rows": 2620,
      "skipped_invalid_quote": 0,
      "skipped_non_0dte": 74920,
      "trade_date": "2023-07-10"
    },
    {
      "file": "data\\raw\\spy_0dte\\databento\\insample_2023_07\\insample_2023_07\\2023-07-10_exit_check_1300.dbn.zst",
      "input_rows": 77540,
      "output_rows": 2620,
      "skipped_invalid_quote": 0,
      "skipped_non_0dte": 74920,
      "trade_date": "2023-07-10"
    },
    {
      "file": "data\\raw\\spy_0dte\\databento\\insample_2023_07\\insample_2023_07\\2023-07-10_exit_check_1330.dbn.zst",
      "input_rows": 77540,
      "output_rows": 2620,
      "skipped_invalid_quote": 0,
      "skipped_non_0dte": 74920,
      "trade_date": "2023-07-10"
    },
    {
      "file": "data\\raw\\spy_0dte\\databento\\insample_2023_07\\insample_2023_07\\2023-07-10_exit_check_1400.dbn.zst",
      "input_rows": 77540,
      "output_rows": 2620,
      "skipped_invalid_quote": 0,
      "skipped_non_0dte": 74920,
      "trade_date": "2023-07-10"
    },
    {
      "file": "data\\raw\\spy_0dte\\databento\\insample_2023_07\\insample_2023_07\\2023-07-10_exit_check_1430.dbn.zst",
      "input_rows": 77540,
      "output_rows": 2620,
      "skipped_invalid_quote": 0,
      "skipped_non_0dte": 74920,
      "trade_date": "2023-07-10"
    },
    {
      "file": "data\\raw\\spy_0dte\\databento\\insample_2023_07\\insample_2023_07\\2023-07-10_exit_check_1500.dbn.zst",
      "input_rows": 77540,
      "output_rows": 2620,
      "skipped_invalid_quote": 0,
      "skipped_non_0dte": 74920,
      "trade_date": "2023-07-10"
    },
    {
      "file": "data\\raw\\spy_0dte\\databento\\insample_2023_07\\insample_2023_07\\2023-07-10_exit_check_1530.dbn.zst",
      "input_rows": 77540,
      "output_rows": 2620,
      "skipped_invalid_quote": 0,
      "skipped_non_0dte": 74920,
      "trade_date": "2023-07-10"
    },
    {
      "file": "data\\raw\\spy_0dte\\databento\\insample_2023_07\\insample_2023_07\\2023-07-10_forced_close_1545.dbn.zst",
      "input_rows": 77540,
      "output_rows": 2620,
      "skipped_invalid_quote": 0,
      "skipped_non_0dte": 74920,
      "trade_date": "2023-07-10"
    },
    {
      "file": "data\\raw\\spy_0dte\\databento\\insample_2023_07\\insample_2023_07\\2023-07-11_entry_a_0935.dbn.zst",
      "input_rows": 68112,
      "output_rows": 2358,
      "skipped_invalid_quote": 0,
      "skipped_non_0dte": 65754,
      "trade_date": "2023-07-11"
    },
    {
      "file": "data\\raw\\spy_0dte\\databento\\insample_2023_07\\insample_2023_07\\2023-07-11_entry_b_1000.dbn.zst",
      "input_rows": 75680,
      "output_rows": 2620,
      "skipped_invalid_quote": 0,
      "skipped_non_0dte": 73060,
      "trade_date": "2023-07-11"
    },
    {
      "file": "data\\raw\\spy_0dte\\databento\\insample_2023_07\\insample_2023_07\\2023-07-11_exit_check_1030.dbn.zst",
      "input_rows": 75680,
      "output_rows": 2620,
      "skipped_invalid_quote": 0,
      "skipped_non_0dte": 73060,
      "trade_date": "2023-07-11"
    },
    {
      "file": "data\\raw\\spy_0dte\\databento\\insample_2023_07\\insample_2023_07\\2023-07-11_exit_check_1100.dbn.zst",
      "input_rows": 75680,
      "output_rows": 2620,
      "skipped_invalid_quote": 0,
      "skipped_non_0dte": 73060,
      "trade_date": "2023-07-11"
    },
    {
      "file": "data\\raw\\spy_0dte\\databento\\insample_2023_07\\insample_2023_07\\2023-07-11_exit_check_1130.dbn.zst",
      "input_rows": 75680,
      "output_rows": 2620,
      "skipped_invalid_quote": 0,
      "skipped_non_0dte": 73060,
      "trade_date": "2023-07-11"
    },
    {
      "file": "data\\raw\\spy_0dte\\databento\\insample_2023_07\\insample_2023_07\\2023-07-11_exit_check_1200.dbn.zst",
      "input_rows": 75680,
      "output_rows": 2620,
      "skipped_invalid_quote": 0,
      "skipped_non_0dte": 73060,
      "trade_date": "2023-07-11"
    },
    {
      "file": "data\\raw\\spy_0dte\\databento\\insample_2023_07\\insample_2023_07\\2023-07-11_exit_check_1230.dbn.zst",
      "input_rows": 75680,
      "output_rows": 2620,
      "skipped_invalid_quote": 0,
      "skipped_non_0dte": 73060,
      "trade_date": "2023-07-11"
    },
    {
      "file": "data\\raw\\spy_0dte\\databento\\insample_2023_07\\insample_2023_07\\2023-07-11_exit_check_1300.dbn.zst",
      "input_rows": 75680,
      "output_rows": 2620,
      "skipped_invalid_quote": 0,
      "skipped_non_0dte": 73060,
      "trade_date": "2023-07-11"
    },
    {
      "file": "data\\raw\\spy_0dte\\databento\\insample_2023_07\\insample_2023_07\\2023-07-11_exit_check_1330.dbn.zst",
      "input_rows": 75680,
      "output_rows": 2620,
      "skipped_invalid_quote": 0,
      "skipped_non_0dte": 73060,
      "trade_date": "2023-07-11"
    },
    {
      "file": "data\\raw\\spy_0dte\\databento\\insample_2023_07\\insample_2023_07\\2023-07-11_exit_check_1400.dbn.zst",
      "input_rows": 75680,
      "output_rows": 2620,
      "skipped_invalid_quote": 0,
      "skipped_non_0dte": 73060,
      "trade_date": "2023-07-11"
    },
    {
      "file": "data\\raw\\spy_0dte\\databento\\insample_2023_07\\insample_2023_07\\2023-07-11_exit_check_1430.dbn.zst",
      "input_rows": 75680,
      "output_rows": 2620,
      "skipped_invalid_quote": 0,
      "skipped_non_0dte": 73060,
      "trade_date": "2023-07-11"
    },
    {
      "file": "data\\raw\\spy_0dte\\databento\\insample_2023_07\\insample_2023_07\\2023-07-11_exit_check_1500.dbn.zst",
      "input_rows": 75680,
      "output_rows": 2620,
      "skipped_invalid_quote": 0,
      "skipped_non_0dte": 73060,
      "trade_date": "2023-07-11"
    },
    {
      "file": "data\\raw\\spy_0dte\\databento\\insample_2023_07\\insample_2023_07\\2023-07-11_exit_check_1530.dbn.zst",
      "input_rows": 75680,
      "output_rows": 2620,
      "skipped_invalid_quote": 0,
      "skipped_non_0dte": 73060,
      "trade_date": "2023-07-11"
    },
    {
      "file": "data\\raw\\spy_0dte\\databento\\insample_2023_07\\insample_2023_07\\2023-07-11_forced_close_1545.dbn.zst",
      "input_rows": 75680,
      "output_rows": 2620,
      "skipped_invalid_quote": 0,
      "skipped_non_0dte": 73060,
      "trade_date": "2023-07-11"
    },
    {
      "file": "data\\raw\\spy_0dte\\databento\\insample_2023_07\\insample_2023_07\\2023-07-12_entry_a_0935.dbn.zst",
      "input_rows": 71766,
      "output_rows": 2358,
      "skipped_invalid_quote": 0,
      "skipped_non_0dte": 69408,
      "trade_date": "2023-07-12"
    },
    {
      "file": "data\\raw\\spy_0dte\\databento\\insample_2023_07\\insample_2023_07\\2023-07-12_entry_b_1000.dbn.zst",
      "input_rows": 79740,
      "output_rows": 2620,
      "skipped_invalid_quote": 0,
      "skipped_non_0dte": 77120,
      "trade_date": "2023-07-12"
    },
    {
      "file": "data\\raw\\spy_0dte\\databento\\insample_2023_07\\insample_2023_07\\2023-07-12_exit_check_1030.dbn.zst",
      "input_rows": 79740,
      "output_rows": 2620,
      "skipped_invalid_quote": 0,
      "skipped_non_0dte": 77120,
      "trade_date": "2023-07-12"
    },
    {
      "file": "data\\raw\\spy_0dte\\databento\\insample_2023_07\\insample_2023_07\\2023-07-12_exit_check_1100.dbn.zst",
      "input_rows": 79740,
      "output_rows": 2620,
      "skipped_invalid_quote": 0,
      "skipped_non_0dte": 77120,
      "trade_date": "2023-07-12"
    },
    {
      "file": "data\\raw\\spy_0dte\\databento\\insample_2023_07\\insample_2023_07\\2023-07-12_exit_check_1130.dbn.zst",
      "input_rows": 79740,
      "output_rows": 2620,
      "skipped_invalid_quote": 0,
      "skipped_non_0dte": 77120,
      "trade_date": "2023-07-12"
    },
    {
      "file": "data\\raw\\spy_0dte\\databento\\insample_2023_07\\insample_2023_07\\2023-07-12_exit_check_1200.dbn.zst",
      "input_rows": 79740,
      "output_rows": 2620,
      "skipped_invalid_quote": 0,
      "skipped_non_0dte": 77120,
      "trade_date": "2023-07-12"
    },
    {
      "file": "data\\raw\\spy_0dte\\databento\\insample_2023_07\\insample_2023_07\\2023-07-12_exit_check_1230.dbn.zst",
      "input_rows": 79740,
      "output_rows": 2620,
      "skipped_invalid_quote": 0,
      "skipped_non_0dte": 77120,
      "trade_date": "2023-07-12"
    },
    {
      "file": "data\\raw\\spy_0dte\\databento\\insample_2023_07\\insample_2023_07\\2023-07-12_exit_check_1300.dbn.zst",
      "input_rows": 79740,
      "output_rows": 2620,
      "skipped_invalid_quote": 0,
      "skipped_non_0dte": 77120,
      "trade_date": "2023-07-12"
    },
    {
      "file": "data\\raw\\spy_0dte\\databento\\insample_2023_07\\insample_2023_07\\2023-07-12_exit_check_1330.dbn.zst",
      "input_rows": 79740,
      "output_rows": 2620,
      "skipped_invalid_quote": 0,
      "skipped_non_0dte": 77120,
      "trade_date": "2023-07-12"
    },
    {
      "file": "data\\raw\\spy_0dte\\databento\\insample_2023_07\\insample_2023_07\\2023-07-12_exit_check_1400.dbn.zst",
      "input_rows": 79740,
      "output_rows": 2620,
      "skipped_invalid_quote": 0,
      "skipped_non_0dte": 77120,
      "trade_date": "2023-07-12"
    },
    {
      "file": "data\\raw\\spy_0dte\\databento\\insample_2023_07\\insample_2023_07\\2023-07-12_exit_check_1430.dbn.zst",
      "input_rows": 79740,
      "output_rows": 2620,
      "skipped_invalid_quote": 0,
      "skipped_non_0dte": 77120,
      "trade_date": "2023-07-12"
    },
    {
      "file": "data\\raw\\spy_0dte\\databento\\insample_2023_07\\insample_2023_07\\2023-07-12_exit_check_1500.dbn.zst",
      "input_rows": 79740,
      "output_rows": 2620,
      "skipped_invalid_quote": 0,
      "skipped_non_0dte": 77120,
      "trade_date": "2023-07-12"
    },
    {
      "file": "data\\raw\\spy_0dte\\databento\\insample_2023_07\\insample_2023_07\\2023-07-12_exit_check_1530.dbn.zst",
      "input_rows": 79740,
      "output_rows": 2620,
      "skipped_invalid_quote": 0,
      "skipped_non_0dte": 77120,
      "trade_date": "2023-07-12"
    },
    {
      "file": "data\\raw\\spy_0dte\\databento\\insample_2023_07\\insample_2023_07\\2023-07-12_forced_close_1545.dbn.zst",
      "input_rows": 79740,
      "output_rows": 2620,
      "skipped_invalid_quote": 0,
      "skipped_non_0dte": 77120,
      "trade_date": "2023-07-12"
    },
    {
      "file": "data\\raw\\spy_0dte\\databento\\insample_2023_07\\insample_2023_07\\2023-07-13_entry_a_0935.dbn.zst",
      "input_rows": 70848,
      "output_rows": 2322,
      "skipped_invalid_quote": 0,
      "skipped_non_0dte": 68526,
      "trade_date": "2023-07-13"
    },
    {
      "file": "data\\raw\\spy_0dte\\databento\\insample_2023_07\\insample_2023_07\\2023-07-13_entry_b_1000.dbn.zst",
      "input_rows": 78720,
      "output_rows": 2580,
      "skipped_invalid_quote": 0,
      "skipped_non_0dte": 76140,
      "trade_date": "2023-07-13"
    },
    {
      "file": "data\\raw\\spy_0dte\\databento\\insample_2023_07\\insample_2023_07\\2023-07-13_exit_check_1030.dbn.zst",
      "input_rows": 78720,
      "output_rows": 2580,
      "skipped_invalid_quote": 0,
      "skipped_non_0dte": 76140,
      "trade_date": "2023-07-13"
    },
    {
      "file": "data\\raw\\spy_0dte\\databento\\insample_2023_07\\insample_2023_07\\2023-07-13_exit_check_1100.dbn.zst",
      "input_rows": 78720,
      "output_rows": 2580,
      "skipped_invalid_quote": 0,
      "skipped_non_0dte": 76140,
      "trade_date": "2023-07-13"
    },
    {
      "file": "data\\raw\\spy_0dte\\databento\\insample_2023_07\\insample_2023_07\\2023-07-13_exit_check_1130.dbn.zst",
      "input_rows": 78720,
      "output_rows": 2580,
      "skipped_invalid_quote": 0,
      "skipped_non_0dte": 76140,
      "trade_date": "2023-07-13"
    },
    {
      "file": "data\\raw\\spy_0dte\\databento\\insample_2023_07\\insample_2023_07\\2023-07-13_exit_check_1200.dbn.zst",
      "input_rows": 78720,
      "output_rows": 2580,
      "skipped_invalid_quote": 0,
      "skipped_non_0dte": 76140,
      "trade_date": "2023-07-13"
    },
    {
      "file": "data\\raw\\spy_0dte\\databento\\insample_2023_07\\insample_2023_07\\2023-07-13_exit_check_1230.dbn.zst",
      "input_rows": 78720,
      "output_rows": 2580,
      "skipped_invalid_quote": 0,
      "skipped_non_0dte": 76140,
      "trade_date": "2023-07-13"
    },
    {
      "file": "data\\raw\\spy_0dte\\databento\\insample_2023_07\\insample_2023_07\\2023-07-13_exit_check_1300.dbn.zst",
      "input_rows": 78720,
      "output_rows": 2580,
      "skipped_invalid_quote": 0,
      "skipped_non_0dte": 76140,
      "trade_date": "2023-07-13"
    },
    {
      "file": "data\\raw\\spy_0dte\\databento\\insample_2023_07\\insample_2023_07\\2023-07-13_exit_check_1330.dbn.zst",
      "input_rows": 78720,
      "output_rows": 2580,
      "skipped_invalid_quote": 0,
      "skipped_non_0dte": 76140,
      "trade_date": "2023-07-13"
    },
    {
      "file": "data\\raw\\spy_0dte\\databento\\insample_2023_07\\insample_2023_07\\2023-07-13_exit_check_1400.dbn.zst",
      "input_rows": 78720,
      "output_rows": 2580,
      "skipped_invalid_quote": 0,
      "skipped_non_0dte": 76140,
      "trade_date": "2023-07-13"
    },
    {
      "file": "data\\raw\\spy_0dte\\databento\\insample_2023_07\\insample_2023_07\\2023-07-13_exit_check_1430.dbn.zst",
      "input_rows": 78720,
      "output_rows": 2580,
      "skipped_invalid_quote": 0,
      "skipped_non_0dte": 76140,
      "trade_date": "2023-07-13"
    },
    {
      "file": "data\\raw\\spy_0dte\\databento\\insample_2023_07\\insample_2023_07\\2023-07-13_exit_check_1500.dbn.zst",
      "input_rows": 78720,
      "output_rows": 2580,
      "skipped_invalid_quote": 0,
      "skipped_non_0dte": 76140,
      "trade_date": "2023-07-13"
    },
    {
      "file": "data\\raw\\spy_0dte\\databento\\insample_2023_07\\insample_2023_07\\2023-07-13_exit_check_1530.dbn.zst",
      "input_rows": 78720,
      "output_rows": 2580,
      "skipped_invalid_quote": 0,
      "skipped_non_0dte": 76140,
      "trade_date": "2023-07-13"
    },
    {
      "file": "data\\raw\\spy_0dte\\databento\\insample_2023_07\\insample_2023_07\\2023-07-13_forced_close_1545.dbn.zst",
      "input_rows": 78720,
      "output_rows": 2580,
      "skipped_invalid_quote": 0,
      "skipped_non_0dte": 76140,
      "trade_date": "2023-07-13"
    },
    {
      "file": "data\\raw\\spy_0dte\\databento\\insample_2023_07\\insample_2023_07\\2023-07-14_entry_a_0935.dbn.zst",
      "input_rows": 74394,
      "output_rows": 2700,
      "skipped_invalid_quote": 0,
      "skipped_non_0dte": 71694,
      "trade_date": "2023-07-14"
    },
    {
      "file": "data\\raw\\spy_0dte\\databento\\insample_2023_07\\insample_2023_07\\2023-07-14_entry_b_1000.dbn.zst",
      "input_rows": 82660,
      "output_rows": 3000,
      "skipped_invalid_quote": 0,
      "skipped_non_0dte": 79660,
      "trade_date": "2023-07-14"
    },
    {
      "file": "data\\raw\\spy_0dte\\databento\\insample_2023_07\\insample_2023_07\\2023-07-14_exit_check_1030.dbn.zst",
      "input_rows": 82660,
      "output_rows": 3000,
      "skipped_invalid_quote": 0,
      "skipped_non_0dte": 79660,
      "trade_date": "2023-07-14"
    },
    {
      "file": "data\\raw\\spy_0dte\\databento\\insample_2023_07\\insample_2023_07\\2023-07-14_exit_check_1100.dbn.zst",
      "input_rows": 82660,
      "output_rows": 3000,
      "skipped_invalid_quote": 0,
      "skipped_non_0dte": 79660,
      "trade_date": "2023-07-14"
    },
    {
      "file": "data\\raw\\spy_0dte\\databento\\insample_2023_07\\insample_2023_07\\2023-07-14_exit_check_1130.dbn.zst",
      "input_rows": 82660,
      "output_rows": 3000,
      "skipped_invalid_quote": 0,
      "skipped_non_0dte": 79660,
      "trade_date": "2023-07-14"
    },
    {
      "file": "data\\raw\\spy_0dte\\databento\\insample_2023_07\\insample_2023_07\\2023-07-14_exit_check_1200.dbn.zst",
      "input_rows": 82660,
      "output_rows": 3000,
      "skipped_invalid_quote": 0,
      "skipped_non_0dte": 79660,
      "trade_date": "2023-07-14"
    },
    {
      "file": "data\\raw\\spy_0dte\\databento\\insample_2023_07\\insample_2023_07\\2023-07-14_exit_check_1230.dbn.zst",
      "input_rows": 82660,
      "output_rows": 3000,
      "skipped_invalid_quote": 0,
      "skipped_non_0dte": 79660,
      "trade_date": "2023-07-14"
    },
    {
      "file": "data\\raw\\spy_0dte\\databento\\insample_2023_07\\insample_2023_07\\2023-07-14_exit_check_1300.dbn.zst",
      "input_rows": 82660,
      "output_rows": 3000,
      "skipped_invalid_quote": 0,
      "skipped_non_0dte": 79660,
      "trade_date": "2023-07-14"
    },
    {
      "file": "data\\raw\\spy_0dte\\databento\\insample_2023_07\\insample_2023_07\\2023-07-14_exit_check_1330.dbn.zst",
      "input_rows": 82660,
      "output_rows": 3000,
      "skipped_invalid_quote": 0,
      "skipped_non_0dte": 79660,
      "trade_date": "2023-07-14"
    },
    {
      "file": "data\\raw\\spy_0dte\\databento\\insample_2023_07\\insample_2023_07\\2023-07-14_exit_check_1400.dbn.zst",
      "input_rows": 82660,
      "output_rows": 3000,
      "skipped_invalid_quote": 0,
      "skipped_non_0dte": 79660,
      "trade_date": "2023-07-14"
    },
    {
      "file": "data\\raw\\spy_0dte\\databento\\insample_2023_07\\insample_2023_07\\2023-07-14_exit_check_1430.dbn.zst",
      "input_rows": 82660,
      "output_rows": 3000,
      "skipped_invalid_quote": 0,
      "skipped_non_0dte": 79660,
      "trade_date": "2023-07-14"
    },
    {
      "file": "data\\raw\\spy_0dte\\databento\\insample_2023_07\\insample_2023_07\\2023-07-14_exit_check_1500.dbn.zst",
      "input_rows": 82660,
      "output_rows": 3000,
      "skipped_invalid_quote": 0,
      "skipped_non_0dte": 79660,
      "trade_date": "2023-07-14"
    },
    {
      "file": "data\\raw\\spy_0dte\\databento\\insample_2023_07\\insample_2023_07\\2023-07-14_exit_check_1530.dbn.zst",
      "input_rows": 82660,
      "output_rows": 3000,
      "skipped_invalid_quote": 0,
      "skipped_non_0dte": 79660,
      "trade_date": "2023-07-14"
    },
    {
      "file": "data\\raw\\spy_0dte\\databento\\insample_2023_07\\insample_2023_07\\2023-07-14_forced_close_1545.dbn.zst",
      "input_rows": 82660,
      "output_rows": 3000,
      "skipped_invalid_quote": 0,
      "skipped_non_0dte": 79660,
      "trade_date": "2023-07-14"
    },
    {
      "file": "data\\raw\\spy_0dte\\databento\\insample_2023_07\\insample_2023_07\\2023-07-17_entry_a_0935.dbn.zst",
      "input_rows": 73242,
      "output_rows": 2340,
      "skipped_invalid_quote": 0,
      "skipped_non_0dte": 70902,
      "trade_date": "2023-07-17"
    },
    {
      "file": "data\\raw\\spy_0dte\\databento\\insample_2023_07\\insample_2023_07\\2023-07-17_entry_b_1000.dbn.zst",
      "input_rows": 81380,
      "output_rows": 2600,
      "skipped_invalid_quote": 0,
      "skipped_non_0dte": 78780,
      "trade_date": "2023-07-17"
    },
    {
      "file": "data\\raw\\spy_0dte\\databento\\insample_2023_07\\insample_2023_07\\2023-07-17_exit_check_1030.dbn.zst",
      "input_rows": 81380,
      "output_rows": 2600,
      "skipped_invalid_quote": 0,
      "skipped_non_0dte": 78780,
      "trade_date": "2023-07-17"
    },
    {
      "file": "data\\raw\\spy_0dte\\databento\\insample_2023_07\\insample_2023_07\\2023-07-17_exit_check_1100.dbn.zst",
      "input_rows": 81380,
      "output_rows": 2600,
      "skipped_invalid_quote": 0,
      "skipped_non_0dte": 78780,
      "trade_date": "2023-07-17"
    },
    {
      "file": "data\\raw\\spy_0dte\\databento\\insample_2023_07\\insample_2023_07\\2023-07-17_exit_check_1130.dbn.zst",
      "input_rows": 81380,
      "output_rows": 2600,
      "skipped_invalid_quote": 0,
      "skipped_non_0dte": 78780,
      "trade_date": "2023-07-17"
    },
    {
      "file": "data\\raw\\spy_0dte\\databento\\insample_2023_07\\insample_2023_07\\2023-07-17_exit_check_1200.dbn.zst",
      "input_rows": 81380,
      "output_rows": 2600,
      "skipped_invalid_quote": 0,
      "skipped_non_0dte": 78780,
      "trade_date": "2023-07-17"
    },
    {
      "file": "data\\raw\\spy_0dte\\databento\\insample_2023_07\\insample_2023_07\\2023-07-17_exit_check_1230.dbn.zst",
      "input_rows": 81380,
      "output_rows": 2600,
      "skipped_invalid_quote": 0,
      "skipped_non_0dte": 78780,
      "trade_date": "2023-07-17"
    },
    {
      "file": "data\\raw\\spy_0dte\\databento\\insample_2023_07\\insample_2023_07\\2023-07-17_exit_check_1300.dbn.zst",
      "input_rows": 81380,
      "output_rows": 2600,
      "skipped_invalid_quote": 0,
      "skipped_non_0dte": 78780,
      "trade_date": "2023-07-17"
    },
    {
      "file": "data\\raw\\spy_0dte\\databento\\insample_2023_07\\insample_2023_07\\2023-07-17_exit_check_1330.dbn.zst",
      "input_rows": 81380,
      "output_rows": 2600,
      "skipped_invalid_quote": 0,
      "skipped_non_0dte": 78780,
      "trade_date": "2023-07-17"
    },
    {
      "file": "data\\raw\\spy_0dte\\databento\\insample_2023_07\\insample_2023_07\\2023-07-17_exit_check_1400.dbn.zst",
      "input_rows": 81380,
      "output_rows": 2600,
      "skipped_invalid_quote": 0,
      "skipped_non_0dte": 78780,
      "trade_date": "2023-07-17"
    },
    {
      "file": "data\\raw\\spy_0dte\\databento\\insample_2023_07\\insample_2023_07\\2023-07-17_exit_check_1430.dbn.zst",
      "input_rows": 81380,
      "output_rows": 2600,
      "skipped_invalid_quote": 0,
      "skipped_non_0dte": 78780,
      "trade_date": "2023-07-17"
    },
    {
      "file": "data\\raw\\spy_0dte\\databento\\insample_2023_07\\insample_2023_07\\2023-07-17_exit_check_1500.dbn.zst",
      "input_rows": 81380,
      "output_rows": 2600,
      "skipped_invalid_quote": 0,
      "skipped_non_0dte": 78780,
      "trade_date": "2023-07-17"
    },
    {
      "file": "data\\raw\\spy_0dte\\databento\\insample_2023_07\\insample_2023_07\\2023-07-17_exit_check_1530.dbn.zst",
      "input_rows": 81380,
      "output_rows": 2600,
      "skipped_invalid_quote": 0,
      "skipped_non_0dte": 78780,
      "trade_date": "2023-07-17"
    },
    {
      "file": "data\\raw\\spy_0dte\\databento\\insample_2023_07\\insample_2023_07\\2023-07-17_forced_close_1545.dbn.zst",
      "input_rows": 81380,
      "output_rows": 2600,
      "skipped_invalid_quote": 0,
      "skipped_non_0dte": 78780,
      "trade_date": "2023-07-17"
    },
    {
      "file": "data\\raw\\spy_0dte\\databento\\insample_2023_07\\insample_2023_07\\2023-07-18_entry_a_0935.dbn.zst",
      "input_rows": 73710,
      "output_rows": 2376,
      "skipped_invalid_quote": 0,
      "skipped_non_0dte": 71334,
      "trade_date": "2023-07-18"
    },
    {
      "file": "data\\raw\\spy_0dte\\databento\\insample_2023_07\\insample_2023_07\\2023-07-18_entry_b_1000.dbn.zst",
      "input_rows": 81900,
      "output_rows": 2640,
      "skipped_invalid_quote": 0,
      "skipped_non_0dte": 79260,
      "trade_date": "2023-07-18"
    },
    {
      "file": "data\\raw\\spy_0dte\\databento\\insample_2023_07\\insample_2023_07\\2023-07-18_exit_check_1030.dbn.zst",
      "input_rows": 81900,
      "output_rows": 2640,
      "skipped_invalid_quote": 0,
      "skipped_non_0dte": 79260,
      "trade_date": "2023-07-18"
    },
    {
      "file": "data\\raw\\spy_0dte\\databento\\insample_2023_07\\insample_2023_07\\2023-07-18_exit_check_1100.dbn.zst",
      "input_rows": 81900,
      "output_rows": 2640,
      "skipped_invalid_quote": 0,
      "skipped_non_0dte": 79260,
      "trade_date": "2023-07-18"
    },
    {
      "file": "data\\raw\\spy_0dte\\databento\\insample_2023_07\\insample_2023_07\\2023-07-18_exit_check_1130.dbn.zst",
      "input_rows": 81900,
      "output_rows": 2640,
      "skipped_invalid_quote": 0,
      "skipped_non_0dte": 79260,
      "trade_date": "2023-07-18"
    },
    {
      "file": "data\\raw\\spy_0dte\\databento\\insample_2023_07\\insample_2023_07\\2023-07-18_exit_check_1200.dbn.zst",
      "input_rows": 81900,
      "output_rows": 2640,
      "skipped_invalid_quote": 0,
      "skipped_non_0dte": 79260,
      "trade_date": "2023-07-18"
    },
    {
      "file": "data\\raw\\spy_0dte\\databento\\insample_2023_07\\insample_2023_07\\2023-07-18_exit_check_1230.dbn.zst",
      "input_rows": 81900,
      "output_rows": 2640,
      "skipped_invalid_quote": 0,
      "skipped_non_0dte": 79260,
      "trade_date": "2023-07-18"
    },
    {
      "file": "data\\raw\\spy_0dte\\databento\\insample_2023_07\\insample_2023_07\\2023-07-18_exit_check_1300.dbn.zst",
      "input_rows": 81900,
      "output_rows": 2640,
      "skipped_invalid_quote": 0,
      "skipped_non_0dte": 79260,
      "trade_date": "2023-07-18"
    },
    {
      "file": "data\\raw\\spy_0dte\\databento\\insample_2023_07\\insample_2023_07\\2023-07-18_exit_check_1330.dbn.zst",
      "input_rows": 81900,
      "output_rows": 2640,
      "skipped_invalid_quote": 0,
      "skipped_non_0dte": 79260,
      "trade_date": "2023-07-18"
    },
    {
      "file": "data\\raw\\spy_0dte\\databento\\insample_2023_07\\insample_2023_07\\2023-07-18_exit_check_1400.dbn.zst",
      "input_rows": 81900,
      "output_rows": 2640,
      "skipped_invalid_quote": 0,
      "skipped_non_0dte": 79260,
      "trade_date": "2023-07-18"
    },
    {
      "file": "data\\raw\\spy_0dte\\databento\\insample_2023_07\\insample_2023_07\\2023-07-18_exit_check_1430.dbn.zst",
      "input_rows": 81900,
      "output_rows": 2640,
      "skipped_invalid_quote": 0,
      "skipped_non_0dte": 79260,
      "trade_date": "2023-07-18"
    },
    {
      "file": "data\\raw\\spy_0dte\\databento\\insample_2023_07\\insample_2023_07\\2023-07-18_exit_check_1500.dbn.zst",
      "input_rows": 81900,
      "output_rows": 2640,
      "skipped_invalid_quote": 0,
      "skipped_non_0dte": 79260,
      "trade_date": "2023-07-18"
    },
    {
      "file": "data\\raw\\spy_0dte\\databento\\insample_2023_07\\insample_2023_07\\2023-07-18_exit_check_1530.dbn.zst",
      "input_rows": 81900,
      "output_rows": 2640,
      "skipped_invalid_quote": 0,
      "skipped_non_0dte": 79260,
      "trade_date": "2023-07-18"
    },
    {
      "file": "data\\raw\\spy_0dte\\databento\\insample_2023_07\\insample_2023_07\\2023-07-18_forced_close_1545.dbn.zst",
      "input_rows": 81900,
      "output_rows": 2640,
      "skipped_invalid_quote": 0,
      "skipped_non_0dte": 79260,
      "trade_date": "2023-07-18"
    },
    {
      "file": "data\\raw\\spy_0dte\\databento\\insample_2023_07\\insample_2023_07\\2023-07-19_entry_a_0935.dbn.zst",
      "input_rows": 72216,
      "output_rows": 2376,
      "skipped_invalid_quote": 0,
      "skipped_non_0dte": 69840,
      "trade_date": "2023-07-19"
    },
    {
      "file": "data\\raw\\spy_0dte\\databento\\insample_2023_07\\insample_2023_07\\2023-07-19_entry_b_1000.dbn.zst",
      "input_rows": 80240,
      "output_rows": 2640,
      "skipped_invalid_quote": 0,
      "skipped_non_0dte": 77600,
      "trade_date": "2023-07-19"
    },
    {
      "file": "data\\raw\\spy_0dte\\databento\\insample_2023_07\\insample_2023_07\\2023-07-19_exit_check_1030.dbn.zst",
      "input_rows": 80240,
      "output_rows": 2640,
      "skipped_invalid_quote": 0,
      "skipped_non_0dte": 77600,
      "trade_date": "2023-07-19"
    },
    {
      "file": "data\\raw\\spy_0dte\\databento\\insample_2023_07\\insample_2023_07\\2023-07-19_exit_check_1100.dbn.zst",
      "input_rows": 80240,
      "output_rows": 2640,
      "skipped_invalid_quote": 0,
      "skipped_non_0dte": 77600,
      "trade_date": "2023-07-19"
    },
    {
      "file": "data\\raw\\spy_0dte\\databento\\insample_2023_07\\insample_2023_07\\2023-07-19_exit_check_1130.dbn.zst",
      "input_rows": 80240,
      "output_rows": 2640,
      "skipped_invalid_quote": 0,
      "skipped_non_0dte": 77600,
      "trade_date": "2023-07-19"
    },
    {
      "file": "data\\raw\\spy_0dte\\databento\\insample_2023_07\\insample_2023_07\\2023-07-19_exit_check_1200.dbn.zst",
      "input_rows": 80240,
      "output_rows": 2640,
      "skipped_invalid_quote": 0,
      "skipped_non_0dte": 77600,
      "trade_date": "2023-07-19"
    },
    {
      "file": "data\\raw\\spy_0dte\\databento\\insample_2023_07\\insample_2023_07\\2023-07-19_exit_check_1230.dbn.zst",
      "input_rows": 80240,
      "output_rows": 2640,
      "skipped_invalid_quote": 0,
      "skipped_non_0dte": 77600,
      "trade_date": "2023-07-19"
    },
    {
      "file": "data\\raw\\spy_0dte\\databento\\insample_2023_07\\insample_2023_07\\2023-07-19_exit_check_1300.dbn.zst",
      "input_rows": 80240,
      "output_rows": 2640,
      "skipped_invalid_quote": 0,
      "skipped_non_0dte": 77600,
      "trade_date": "2023-07-19"
    },
    {
      "file": "data\\raw\\spy_0dte\\databento\\insample_2023_07\\insample_2023_07\\2023-07-19_exit_check_1330.dbn.zst",
      "input_rows": 80240,
      "output_rows": 2640,
      "skipped_invalid_quote": 0,
      "skipped_non_0dte": 77600,
      "trade_date": "2023-07-19"
    },
    {
      "file": "data\\raw\\spy_0dte\\databento\\insample_2023_07\\insample_2023_07\\2023-07-19_exit_check_1400.dbn.zst",
      "input_rows": 80240,
      "output_rows": 2640,
      "skipped_invalid_quote": 0,
      "skipped_non_0dte": 77600,
      "trade_date": "2023-07-19"
    },
    {
      "file": "data\\raw\\spy_0dte\\databento\\insample_2023_07\\insample_2023_07\\2023-07-19_exit_check_1430.dbn.zst",
      "input_rows": 80240,
      "output_rows": 2640,
      "skipped_invalid_quote": 0,
      "skipped_non_0dte": 77600,
      "trade_date": "2023-07-19"
    },
    {
      "file": "data\\raw\\spy_0dte\\databento\\insample_2023_07\\insample_2023_07\\2023-07-19_exit_check_1500.dbn.zst",
      "input_rows": 80240,
      "output_rows": 2640,
      "skipped_invalid_quote": 0,
      "skipped_non_0dte": 77600,
      "trade_date": "2023-07-19"
    },
    {
      "file": "data\\raw\\spy_0dte\\databento\\insample_2023_07\\insample_2023_07\\2023-07-19_exit_check_1530.dbn.zst",
      "input_rows": 80240,
      "output_rows": 2640,
      "skipped_invalid_quote": 0,
      "skipped_non_0dte": 77600,
      "trade_date": "2023-07-19"
    },
    {
      "file": "data\\raw\\spy_0dte\\databento\\insample_2023_07\\insample_2023_07\\2023-07-19_forced_close_1545.dbn.zst",
      "input_rows": 80240,
      "output_rows": 2640,
      "skipped_invalid_quote": 0,
      "skipped_non_0dte": 77600,
      "trade_date": "2023-07-19"
    },
    {
      "file": "data\\raw\\spy_0dte\\databento\\insample_2023_07\\insample_2023_07\\2023-07-20_entry_a_0935.dbn.zst",
      "input_rows": 70596,
      "output_rows": 2376,
      "skipped_invalid_quote": 0,
      "skipped_non_0dte": 68220,
      "trade_date": "2023-07-20"
    },
    {
      "file": "data\\raw\\spy_0dte\\databento\\insample_2023_07\\insample_2023_07\\2023-07-20_entry_b_1000.dbn.zst",
      "input_rows": 78440,
      "output_rows": 2640,
      "skipped_invalid_quote": 0,
      "skipped_non_0dte": 75800,
      "trade_date": "2023-07-20"
    },
    {
      "file": "data\\raw\\spy_0dte\\databento\\insample_2023_07\\insample_2023_07\\2023-07-20_exit_check_1030.dbn.zst",
      "input_rows": 78440,
      "output_rows": 2640,
      "skipped_invalid_quote": 0,
      "skipped_non_0dte": 75800,
      "trade_date": "2023-07-20"
    },
    {
      "file": "data\\raw\\spy_0dte\\databento\\insample_2023_07\\insample_2023_07\\2023-07-20_exit_check_1100.dbn.zst",
      "input_rows": 78440,
      "output_rows": 2640,
      "skipped_invalid_quote": 0,
      "skipped_non_0dte": 75800,
      "trade_date": "2023-07-20"
    },
    {
      "file": "data\\raw\\spy_0dte\\databento\\insample_2023_07\\insample_2023_07\\2023-07-20_exit_check_1130.dbn.zst",
      "input_rows": 78440,
      "output_rows": 2640,
      "skipped_invalid_quote": 0,
      "skipped_non_0dte": 75800,
      "trade_date": "2023-07-20"
    },
    {
      "file": "data\\raw\\spy_0dte\\databento\\insample_2023_07\\insample_2023_07\\2023-07-20_exit_check_1200.dbn.zst",
      "input_rows": 78440,
      "output_rows": 2640,
      "skipped_invalid_quote": 0,
      "skipped_non_0dte": 75800,
      "trade_date": "2023-07-20"
    },
    {
      "file": "data\\raw\\spy_0dte\\databento\\insample_2023_07\\insample_2023_07\\2023-07-20_exit_check_1230.dbn.zst",
      "input_rows": 78440,
      "output_rows": 2640,
      "skipped_invalid_quote": 0,
      "skipped_non_0dte": 75800,
      "trade_date": "2023-07-20"
    },
    {
      "file": "data\\raw\\spy_0dte\\databento\\insample_2023_07\\insample_2023_07\\2023-07-20_exit_check_1300.dbn.zst",
      "input_rows": 78440,
      "output_rows": 2640,
      "skipped_invalid_quote": 0,
      "skipped_non_0dte": 75800,
      "trade_date": "2023-07-20"
    },
    {
      "file": "data\\raw\\spy_0dte\\databento\\insample_2023_07\\insample_2023_07\\2023-07-20_exit_check_1330.dbn.zst",
      "input_rows": 78440,
      "output_rows": 2640,
      "skipped_invalid_quote": 0,
      "skipped_non_0dte": 75800,
      "trade_date": "2023-07-20"
    },
    {
      "file": "data\\raw\\spy_0dte\\databento\\insample_2023_07\\insample_2023_07\\2023-07-20_exit_check_1400.dbn.zst",
      "input_rows": 78440,
      "output_rows": 2640,
      "skipped_invalid_quote": 0,
      "skipped_non_0dte": 75800,
      "trade_date": "2023-07-20"
    },
    {
      "file": "data\\raw\\spy_0dte\\databento\\insample_2023_07\\insample_2023_07\\2023-07-20_exit_check_1430.dbn.zst",
      "input_rows": 78440,
      "output_rows": 2640,
      "skipped_invalid_quote": 0,
      "skipped_non_0dte": 75800,
      "trade_date": "2023-07-20"
    },
    {
      "file": "data\\raw\\spy_0dte\\databento\\insample_2023_07\\insample_2023_07\\2023-07-20_exit_check_1500.dbn.zst",
      "input_rows": 78440,
      "output_rows": 2640,
      "skipped_invalid_quote": 0,
      "skipped_non_0dte": 75800,
      "trade_date": "2023-07-20"
    },
    {
      "file": "data\\raw\\spy_0dte\\databento\\insample_2023_07\\insample_2023_07\\2023-07-20_exit_check_1530.dbn.zst",
      "input_rows": 78440,
      "output_rows": 2640,
      "skipped_invalid_quote": 0,
      "skipped_non_0dte": 75800,
      "trade_date": "2023-07-20"
    },
    {
      "file": "data\\raw\\spy_0dte\\databento\\insample_2023_07\\insample_2023_07\\2023-07-20_forced_close_1545.dbn.zst",
      "input_rows": 78440,
      "output_rows": 2640,
      "skipped_invalid_quote": 0,
      "skipped_non_0dte": 75800,
      "trade_date": "2023-07-20"
    },
    {
      "file": "data\\raw\\spy_0dte\\databento\\insample_2023_07\\insample_2023_07\\2023-07-21_entry_a_0935.dbn.zst",
      "input_rows": 71514,
      "output_rows": 3834,
      "skipped_invalid_quote": 0,
      "skipped_non_0dte": 67680,
      "trade_date": "2023-07-21"
    },
    {
      "file": "data\\raw\\spy_0dte\\databento\\insample_2023_07\\insample_2023_07\\2023-07-21_entry_b_1000.dbn.zst",
      "input_rows": 79460,
      "output_rows": 4260,
      "skipped_invalid_quote": 0,
      "skipped_non_0dte": 75200,
      "trade_date": "2023-07-21"
    },
    {
      "file": "data\\raw\\spy_0dte\\databento\\insample_2023_07\\insample_2023_07\\2023-07-21_exit_check_1030.dbn.zst",
      "input_rows": 79460,
      "output_rows": 4260,
      "skipped_invalid_quote": 0,
      "skipped_non_0dte": 75200,
      "trade_date": "2023-07-21"
    },
    {
      "file": "data\\raw\\spy_0dte\\databento\\insample_2023_07\\insample_2023_07\\2023-07-21_exit_check_1100.dbn.zst",
      "input_rows": 79460,
      "output_rows": 4260,
      "skipped_invalid_quote": 0,
      "skipped_non_0dte": 75200,
      "trade_date": "2023-07-21"
    },
    {
      "file": "data\\raw\\spy_0dte\\databento\\insample_2023_07\\insample_2023_07\\2023-07-21_exit_check_1130.dbn.zst",
      "input_rows": 79460,
      "output_rows": 4260,
      "skipped_invalid_quote": 0,
      "skipped_non_0dte": 75200,
      "trade_date": "2023-07-21"
    },
    {
      "file": "data\\raw\\spy_0dte\\databento\\insample_2023_07\\insample_2023_07\\2023-07-21_exit_check_1200.dbn.zst",
      "input_rows": 79460,
      "output_rows": 4260,
      "skipped_invalid_quote": 0,
      "skipped_non_0dte": 75200,
      "trade_date": "2023-07-21"
    },
    {
      "file": "data\\raw\\spy_0dte\\databento\\insample_2023_07\\insample_2023_07\\2023-07-21_exit_check_1230.dbn.zst",
      "input_rows": 79460,
      "output_rows": 4260,
      "skipped_invalid_quote": 0,
      "skipped_non_0dte": 75200,
      "trade_date": "2023-07-21"
    },
    {
      "file": "data\\raw\\spy_0dte\\databento\\insample_2023_07\\insample_2023_07\\2023-07-21_exit_check_1300.dbn.zst",
      "input_rows": 79460,
      "output_rows": 4260,
      "skipped_invalid_quote": 0,
      "skipped_non_0dte": 75200,
      "trade_date": "2023-07-21"
    },
    {
      "file": "data\\raw\\spy_0dte\\databento\\insample_2023_07\\insample_2023_07\\2023-07-21_exit_check_1330.dbn.zst",
      "input_rows": 79460,
      "output_rows": 4260,
      "skipped_invalid_quote": 0,
      "skipped_non_0dte": 75200,
      "trade_date": "2023-07-21"
    },
    {
      "file": "data\\raw\\spy_0dte\\databento\\insample_2023_07\\insample_2023_07\\2023-07-21_exit_check_1400.dbn.zst",
      "input_rows": 79460,
      "output_rows": 4260,
      "skipped_invalid_quote": 0,
      "skipped_non_0dte": 75200,
      "trade_date": "2023-07-21"
    },
    {
      "file": "data\\raw\\spy_0dte\\databento\\insample_2023_07\\insample_2023_07\\2023-07-21_exit_check_1430.dbn.zst",
      "input_rows": 79460,
      "output_rows": 4260,
      "skipped_invalid_quote": 0,
      "skipped_non_0dte": 75200,
      "trade_date": "2023-07-21"
    },
    {
      "file": "data\\raw\\spy_0dte\\databento\\insample_2023_07\\insample_2023_07\\2023-07-21_exit_check_1500.dbn.zst",
      "input_rows": 79460,
      "output_rows": 4260,
      "skipped_invalid_quote": 0,
      "skipped_non_0dte": 75200,
      "trade_date": "2023-07-21"
    },
    {
      "file": "data\\raw\\spy_0dte\\databento\\insample_2023_07\\insample_2023_07\\2023-07-21_exit_check_1530.dbn.zst",
      "input_rows": 79460,
      "output_rows": 4260,
      "skipped_invalid_quote": 0,
      "skipped_non_0dte": 75200,
      "trade_date": "2023-07-21"
    },
    {
      "file": "data\\raw\\spy_0dte\\databento\\insample_2023_07\\insample_2023_07\\2023-07-21_forced_close_1545.dbn.zst",
      "input_rows": 79460,
      "output_rows": 4260,
      "skipped_invalid_quote": 0,
      "skipped_non_0dte": 75200,
      "trade_date": "2023-07-21"
    },
    {
      "file": "data\\raw\\spy_0dte\\databento\\insample_2023_07\\insample_2023_07\\2023-07-24_entry_a_0935.dbn.zst",
      "input_rows": 69120,
      "output_rows": 2394,
      "skipped_invalid_quote": 0,
      "skipped_non_0dte": 66726,
      "trade_date": "2023-07-24"
    },
    {
      "file": "data\\raw\\spy_0dte\\databento\\insample_2023_07\\insample_2023_07\\2023-07-24_entry_b_1000.dbn.zst",
      "input_rows": 76800,
      "output_rows": 2660,
      "skipped_invalid_quote": 0,
      "skipped_non_0dte": 74140,
      "trade_date": "2023-07-24"
    },
    {
      "file": "data\\raw\\spy_0dte\\databento\\insample_2023_07\\insample_2023_07\\2023-07-24_exit_check_1030.dbn.zst",
      "input_rows": 76800,
      "output_rows": 2660,
      "skipped_invalid_quote": 0,
      "skipped_non_0dte": 74140,
      "trade_date": "2023-07-24"
    },
    {
      "file": "data\\raw\\spy_0dte\\databento\\insample_2023_07\\insample_2023_07\\2023-07-24_exit_check_1100.dbn.zst",
      "input_rows": 76800,
      "output_rows": 2660,
      "skipped_invalid_quote": 0,
      "skipped_non_0dte": 74140,
      "trade_date": "2023-07-24"
    },
    {
      "file": "data\\raw\\spy_0dte\\databento\\insample_2023_07\\insample_2023_07\\2023-07-24_exit_check_1130.dbn.zst",
      "input_rows": 76800,
      "output_rows": 2660,
      "skipped_invalid_quote": 0,
      "skipped_non_0dte": 74140,
      "trade_date": "2023-07-24"
    },
    {
      "file": "data\\raw\\spy_0dte\\databento\\insample_2023_07\\insample_2023_07\\2023-07-24_exit_check_1200.dbn.zst",
      "input_rows": 76800,
      "output_rows": 2660,
      "skipped_invalid_quote": 0,
      "skipped_non_0dte": 74140,
      "trade_date": "2023-07-24"
    },
    {
      "file": "data\\raw\\spy_0dte\\databento\\insample_2023_07\\insample_2023_07\\2023-07-24_exit_check_1230.dbn.zst",
      "input_rows": 76800,
      "output_rows": 2660,
      "skipped_invalid_quote": 0,
      "skipped_non_0dte": 74140,
      "trade_date": "2023-07-24"
    },
    {
      "file": "data\\raw\\spy_0dte\\databento\\insample_2023_07\\insample_2023_07\\2023-07-24_exit_check_1300.dbn.zst",
      "input_rows": 76800,
      "output_rows": 2660,
      "skipped_invalid_quote": 0,
      "skipped_non_0dte": 74140,
      "trade_date": "2023-07-24"
    },
    {
      "file": "data\\raw\\spy_0dte\\databento\\insample_2023_07\\insample_2023_07\\2023-07-24_exit_check_1330.dbn.zst",
      "input_rows": 76800,
      "output_rows": 2660,
      "skipped_invalid_quote": 0,
      "skipped_non_0dte": 74140,
      "trade_date": "2023-07-24"
    },
    {
      "file": "data\\raw\\spy_0dte\\databento\\insample_2023_07\\insample_2023_07\\2023-07-24_exit_check_1400.dbn.zst",
      "input_rows": 76800,
      "output_rows": 2660,
      "skipped_invalid_quote": 0,
      "skipped_non_0dte": 74140,
      "trade_date": "2023-07-24"
    },
    {
      "file": "data\\raw\\spy_0dte\\databento\\insample_2023_07\\insample_2023_07\\2023-07-24_exit_check_1430.dbn.zst",
      "input_rows": 76800,
      "output_rows": 2660,
      "skipped_invalid_quote": 0,
      "skipped_non_0dte": 74140,
      "trade_date": "2023-07-24"
    },
    {
      "file": "data\\raw\\spy_0dte\\databento\\insample_2023_07\\insample_2023_07\\2023-07-24_exit_check_1500.dbn.zst",
      "input_rows": 76800,
      "output_rows": 2660,
      "skipped_invalid_quote": 0,
      "skipped_non_0dte": 74140,
      "trade_date": "2023-07-24"
    },
    {
      "file": "data\\raw\\spy_0dte\\databento\\insample_2023_07\\insample_2023_07\\2023-07-24_exit_check_1530.dbn.zst",
      "input_rows": 76800,
      "output_rows": 2660,
      "skipped_invalid_quote": 0,
      "skipped_non_0dte": 74140,
      "trade_date": "2023-07-24"
    },
    {
      "file": "data\\raw\\spy_0dte\\databento\\insample_2023_07\\insample_2023_07\\2023-07-24_forced_close_1545.dbn.zst",
      "input_rows": 76800,
      "output_rows": 2660,
      "skipped_invalid_quote": 0,
      "skipped_non_0dte": 74140,
      "trade_date": "2023-07-24"
    },
    {
      "file": "data\\raw\\spy_0dte\\databento\\insample_2023_07\\insample_2023_07\\2023-07-25_entry_a_0935.dbn.zst",
      "input_rows": 67410,
      "output_rows": 2394,
      "skipped_invalid_quote": 0,
      "skipped_non_0dte": 65016,
      "trade_date": "2023-07-25"
    },
    {
      "file": "data\\raw\\spy_0dte\\databento\\insample_2023_07\\insample_2023_07\\2023-07-25_entry_b_1000.dbn.zst",
      "input_rows": 74900,
      "output_rows": 2660,
      "skipped_invalid_quote": 0,
      "skipped_non_0dte": 72240,
      "trade_date": "2023-07-25"
    },
    {
      "file": "data\\raw\\spy_0dte\\databento\\insample_2023_07\\insample_2023_07\\2023-07-25_exit_check_1030.dbn.zst",
      "input_rows": 74900,
      "output_rows": 2660,
      "skipped_invalid_quote": 0,
      "skipped_non_0dte": 72240,
      "trade_date": "2023-07-25"
    },
    {
      "file": "data\\raw\\spy_0dte\\databento\\insample_2023_07\\insample_2023_07\\2023-07-25_exit_check_1100.dbn.zst",
      "input_rows": 74900,
      "output_rows": 2660,
      "skipped_invalid_quote": 0,
      "skipped_non_0dte": 72240,
      "trade_date": "2023-07-25"
    },
    {
      "file": "data\\raw\\spy_0dte\\databento\\insample_2023_07\\insample_2023_07\\2023-07-25_exit_check_1130.dbn.zst",
      "input_rows": 74900,
      "output_rows": 2660,
      "skipped_invalid_quote": 0,
      "skipped_non_0dte": 72240,
      "trade_date": "2023-07-25"
    },
    {
      "file": "data\\raw\\spy_0dte\\databento\\insample_2023_07\\insample_2023_07\\2023-07-25_exit_check_1200.dbn.zst",
      "input_rows": 74900,
      "output_rows": 2660,
      "skipped_invalid_quote": 0,
      "skipped_non_0dte": 72240,
      "trade_date": "2023-07-25"
    },
    {
      "file": "data\\raw\\spy_0dte\\databento\\insample_2023_07\\insample_2023_07\\2023-07-25_exit_check_1230.dbn.zst",
      "input_rows": 74900,
      "output_rows": 2660,
      "skipped_invalid_quote": 0,
      "skipped_non_0dte": 72240,
      "trade_date": "2023-07-25"
    },
    {
      "file": "data\\raw\\spy_0dte\\databento\\insample_2023_07\\insample_2023_07\\2023-07-25_exit_check_1300.dbn.zst",
      "input_rows": 74900,
      "output_rows": 2660,
      "skipped_invalid_quote": 0,
      "skipped_non_0dte": 72240,
      "trade_date": "2023-07-25"
    },
    {
      "file": "data\\raw\\spy_0dte\\databento\\insample_2023_07\\insample_2023_07\\2023-07-25_exit_check_1330.dbn.zst",
      "input_rows": 74900,
      "output_rows": 2660,
      "skipped_invalid_quote": 0,
      "skipped_non_0dte": 72240,
      "trade_date": "2023-07-25"
    },
    {
      "file": "data\\raw\\spy_0dte\\databento\\insample_2023_07\\insample_2023_07\\2023-07-25_exit_check_1400.dbn.zst",
      "input_rows": 74900,
      "output_rows": 2660,
      "skipped_invalid_quote": 0,
      "skipped_non_0dte": 72240,
      "trade_date": "2023-07-25"
    },
    {
      "file": "data\\raw\\spy_0dte\\databento\\insample_2023_07\\insample_2023_07\\2023-07-25_exit_check_1430.dbn.zst",
      "input_rows": 74900,
      "output_rows": 2660,
      "skipped_invalid_quote": 0,
      "skipped_non_0dte": 72240,
      "trade_date": "2023-07-25"
    },
    {
      "file": "data\\raw\\spy_0dte\\databento\\insample_2023_07\\insample_2023_07\\2023-07-25_exit_check_1500.dbn.zst",
      "input_rows": 74900,
      "output_rows": 2660,
      "skipped_invalid_quote": 0,
      "skipped_non_0dte": 72240,
      "trade_date": "2023-07-25"
    },
    {
      "file": "data\\raw\\spy_0dte\\databento\\insample_2023_07\\insample_2023_07\\2023-07-25_exit_check_1530.dbn.zst",
      "input_rows": 74900,
      "output_rows": 2660,
      "skipped_invalid_quote": 0,
      "skipped_non_0dte": 72240,
      "trade_date": "2023-07-25"
    },
    {
      "file": "data\\raw\\spy_0dte\\databento\\insample_2023_07\\insample_2023_07\\2023-07-25_forced_close_1545.dbn.zst",
      "input_rows": 74900,
      "output_rows": 2660,
      "skipped_invalid_quote": 0,
      "skipped_non_0dte": 72240,
      "trade_date": "2023-07-25"
    },
    {
      "file": "data\\raw\\spy_0dte\\databento\\insample_2023_07\\insample_2023_07\\2023-07-26_entry_a_0935.dbn.zst",
      "input_rows": 65556,
      "output_rows": 2268,
      "skipped_invalid_quote": 0,
      "skipped_non_0dte": 63288,
      "trade_date": "2023-07-26"
    },
    {
      "file": "data\\raw\\spy_0dte\\databento\\insample_2023_07\\insample_2023_07\\2023-07-26_entry_b_1000.dbn.zst",
      "input_rows": 72840,
      "output_rows": 2520,
      "skipped_invalid_quote": 0,
      "skipped_non_0dte": 70320,
      "trade_date": "2023-07-26"
    },
    {
      "file": "data\\raw\\spy_0dte\\databento\\insample_2023_07\\insample_2023_07\\2023-07-26_exit_check_1030.dbn.zst",
      "input_rows": 72840,
      "output_rows": 2520,
      "skipped_invalid_quote": 0,
      "skipped_non_0dte": 70320,
      "trade_date": "2023-07-26"
    },
    {
      "file": "data\\raw\\spy_0dte\\databento\\insample_2023_07\\insample_2023_07\\2023-07-26_exit_check_1100.dbn.zst",
      "input_rows": 72840,
      "output_rows": 2520,
      "skipped_invalid_quote": 0,
      "skipped_non_0dte": 70320,
      "trade_date": "2023-07-26"
    },
    {
      "file": "data\\raw\\spy_0dte\\databento\\insample_2023_07\\insample_2023_07\\2023-07-26_exit_check_1130.dbn.zst",
      "input_rows": 72840,
      "output_rows": 2520,
      "skipped_invalid_quote": 0,
      "skipped_non_0dte": 70320,
      "trade_date": "2023-07-26"
    },
    {
      "file": "data\\raw\\spy_0dte\\databento\\insample_2023_07\\insample_2023_07\\2023-07-26_exit_check_1200.dbn.zst",
      "input_rows": 72840,
      "output_rows": 2520,
      "skipped_invalid_quote": 0,
      "skipped_non_0dte": 70320,
      "trade_date": "2023-07-26"
    },
    {
      "file": "data\\raw\\spy_0dte\\databento\\insample_2023_07\\insample_2023_07\\2023-07-26_exit_check_1230.dbn.zst",
      "input_rows": 72840,
      "output_rows": 2520,
      "skipped_invalid_quote": 0,
      "skipped_non_0dte": 70320,
      "trade_date": "2023-07-26"
    },
    {
      "file": "data\\raw\\spy_0dte\\databento\\insample_2023_07\\insample_2023_07\\2023-07-26_exit_check_1300.dbn.zst",
      "input_rows": 72840,
      "output_rows": 2520,
      "skipped_invalid_quote": 0,
      "skipped_non_0dte": 70320,
      "trade_date": "2023-07-26"
    },
    {
      "file": "data\\raw\\spy_0dte\\databento\\insample_2023_07\\insample_2023_07\\2023-07-26_exit_check_1330.dbn.zst",
      "input_rows": 72840,
      "output_rows": 2520,
      "skipped_invalid_quote": 0,
      "skipped_non_0dte": 70320,
      "trade_date": "2023-07-26"
    },
    {
      "file": "data\\raw\\spy_0dte\\databento\\insample_2023_07\\insample_2023_07\\2023-07-26_exit_check_1400.dbn.zst",
      "input_rows": 72840,
      "output_rows": 2520,
      "skipped_invalid_quote": 0,
      "skipped_non_0dte": 70320,
      "trade_date": "2023-07-26"
    },
    {
      "file": "data\\raw\\spy_0dte\\databento\\insample_2023_07\\insample_2023_07\\2023-07-26_exit_check_1430.dbn.zst",
      "input_rows": 72840,
      "output_rows": 2520,
      "skipped_invalid_quote": 0,
      "skipped_non_0dte": 70320,
      "trade_date": "2023-07-26"
    },
    {
      "file": "data\\raw\\spy_0dte\\databento\\insample_2023_07\\insample_2023_07\\2023-07-26_exit_check_1500.dbn.zst",
      "input_rows": 72840,
      "output_rows": 2520,
      "skipped_invalid_quote": 0,
      "skipped_non_0dte": 70320,
      "trade_date": "2023-07-26"
    },
    {
      "file": "data\\raw\\spy_0dte\\databento\\insample_2023_07\\insample_2023_07\\2023-07-26_exit_check_1530.dbn.zst",
      "input_rows": 72840,
      "output_rows": 2520,
      "skipped_invalid_quote": 0,
      "skipped_non_0dte": 70320,
      "trade_date": "2023-07-26"
    },
    {
      "file": "data\\raw\\spy_0dte\\databento\\insample_2023_07\\insample_2023_07\\2023-07-26_forced_close_1545.dbn.zst",
      "input_rows": 72840,
      "output_rows": 2520,
      "skipped_invalid_quote": 0,
      "skipped_non_0dte": 70320,
      "trade_date": "2023-07-26"
    },
    {
      "file": "data\\raw\\spy_0dte\\databento\\insample_2023_07\\insample_2023_07\\2023-07-27_entry_a_0935.dbn.zst",
      "input_rows": 64764,
      "output_rows": 2250,
      "skipped_invalid_quote": 0,
      "skipped_non_0dte": 62514,
      "trade_date": "2023-07-27"
    },
    {
      "file": "data\\raw\\spy_0dte\\databento\\insample_2023_07\\insample_2023_07\\2023-07-27_entry_b_1000.dbn.zst",
      "input_rows": 71960,
      "output_rows": 2500,
      "skipped_invalid_quote": 0,
      "skipped_non_0dte": 69460,
      "trade_date": "2023-07-27"
    },
    {
      "file": "data\\raw\\spy_0dte\\databento\\insample_2023_07\\insample_2023_07\\2023-07-27_exit_check_1030.dbn.zst",
      "input_rows": 71960,
      "output_rows": 2500,
      "skipped_invalid_quote": 0,
      "skipped_non_0dte": 69460,
      "trade_date": "2023-07-27"
    },
    {
      "file": "data\\raw\\spy_0dte\\databento\\insample_2023_07\\insample_2023_07\\2023-07-27_exit_check_1100.dbn.zst",
      "input_rows": 71960,
      "output_rows": 2500,
      "skipped_invalid_quote": 0,
      "skipped_non_0dte": 69460,
      "trade_date": "2023-07-27"
    },
    {
      "file": "data\\raw\\spy_0dte\\databento\\insample_2023_07\\insample_2023_07\\2023-07-27_exit_check_1130.dbn.zst",
      "input_rows": 71960,
      "output_rows": 2500,
      "skipped_invalid_quote": 0,
      "skipped_non_0dte": 69460,
      "trade_date": "2023-07-27"
    },
    {
      "file": "data\\raw\\spy_0dte\\databento\\insample_2023_07\\insample_2023_07\\2023-07-27_exit_check_1200.dbn.zst",
      "input_rows": 71960,
      "output_rows": 2500,
      "skipped_invalid_quote": 0,
      "skipped_non_0dte": 69460,
      "trade_date": "2023-07-27"
    },
    {
      "file": "data\\raw\\spy_0dte\\databento\\insample_2023_07\\insample_2023_07\\2023-07-27_exit_check_1230.dbn.zst",
      "input_rows": 71960,
      "output_rows": 2500,
      "skipped_invalid_quote": 0,
      "skipped_non_0dte": 69460,
      "trade_date": "2023-07-27"
    },
    {
      "file": "data\\raw\\spy_0dte\\databento\\insample_2023_07\\insample_2023_07\\2023-07-27_exit_check_1300.dbn.zst",
      "input_rows": 71960,
      "output_rows": 2500,
      "skipped_invalid_quote": 0,
      "skipped_non_0dte": 69460,
      "trade_date": "2023-07-27"
    },
    {
      "file": "data\\raw\\spy_0dte\\databento\\insample_2023_07\\insample_2023_07\\2023-07-27_exit_check_1330.dbn.zst",
      "input_rows": 71960,
      "output_rows": 2500,
      "skipped_invalid_quote": 0,
      "skipped_non_0dte": 69460,
      "trade_date": "2023-07-27"
    },
    {
      "file": "data\\raw\\spy_0dte\\databento\\insample_2023_07\\insample_2023_07\\2023-07-27_exit_check_1400.dbn.zst",
      "input_rows": 71960,
      "output_rows": 2500,
      "skipped_invalid_quote": 0,
      "skipped_non_0dte": 69460,
      "trade_date": "2023-07-27"
    },
    {
      "file": "data\\raw\\spy_0dte\\databento\\insample_2023_07\\insample_2023_07\\2023-07-27_exit_check_1430.dbn.zst",
      "input_rows": 71960,
      "output_rows": 2500,
      "skipped_invalid_quote": 0,
      "skipped_non_0dte": 69460,
      "trade_date": "2023-07-27"
    },
    {
      "file": "data\\raw\\spy_0dte\\databento\\insample_2023_07\\insample_2023_07\\2023-07-27_exit_check_1500.dbn.zst",
      "input_rows": 71960,
      "output_rows": 2500,
      "skipped_invalid_quote": 0,
      "skipped_non_0dte": 69460,
      "trade_date": "2023-07-27"
    },
    {
      "file": "data\\raw\\spy_0dte\\databento\\insample_2023_07\\insample_2023_07\\2023-07-27_exit_check_1530.dbn.zst",
      "input_rows": 71960,
      "output_rows": 2500,
      "skipped_invalid_quote": 0,
      "skipped_non_0dte": 69460,
      "trade_date": "2023-07-27"
    },
    {
      "file": "data\\raw\\spy_0dte\\databento\\insample_2023_07\\insample_2023_07\\2023-07-27_forced_close_1545.dbn.zst",
      "input_rows": 71960,
      "output_rows": 2500,
      "skipped_invalid_quote": 0,
      "skipped_non_0dte": 69460,
      "trade_date": "2023-07-27"
    },
    {
      "file": "data\\raw\\spy_0dte\\databento\\insample_2023_07\\insample_2023_07\\2023-07-28_entry_a_0935.dbn.zst",
      "input_rows": 71370,
      "output_rows": 2592,
      "skipped_invalid_quote": 0,
      "skipped_non_0dte": 68778,
      "trade_date": "2023-07-28"
    },
    {
      "file": "data\\raw\\spy_0dte\\databento\\insample_2023_07\\insample_2023_07\\2023-07-28_entry_b_1000.dbn.zst",
      "input_rows": 79300,
      "output_rows": 2880,
      "skipped_invalid_quote": 0,
      "skipped_non_0dte": 76420,
      "trade_date": "2023-07-28"
    },
    {
      "file": "data\\raw\\spy_0dte\\databento\\insample_2023_07\\insample_2023_07\\2023-07-28_exit_check_1030.dbn.zst",
      "input_rows": 79300,
      "output_rows": 2880,
      "skipped_invalid_quote": 0,
      "skipped_non_0dte": 76420,
      "trade_date": "2023-07-28"
    },
    {
      "file": "data\\raw\\spy_0dte\\databento\\insample_2023_07\\insample_2023_07\\2023-07-28_exit_check_1100.dbn.zst",
      "input_rows": 79300,
      "output_rows": 2880,
      "skipped_invalid_quote": 0,
      "skipped_non_0dte": 76420,
      "trade_date": "2023-07-28"
    },
    {
      "file": "data\\raw\\spy_0dte\\databento\\insample_2023_07\\insample_2023_07\\2023-07-28_exit_check_1130.dbn.zst",
      "input_rows": 79300,
      "output_rows": 2880,
      "skipped_invalid_quote": 0,
      "skipped_non_0dte": 76420,
      "trade_date": "2023-07-28"
    },
    {
      "file": "data\\raw\\spy_0dte\\databento\\insample_2023_07\\insample_2023_07\\2023-07-28_exit_check_1200.dbn.zst",
      "input_rows": 79300,
      "output_rows": 2880,
      "skipped_invalid_quote": 0,
      "skipped_non_0dte": 76420,
      "trade_date": "2023-07-28"
    },
    {
      "file": "data\\raw\\spy_0dte\\databento\\insample_2023_07\\insample_2023_07\\2023-07-28_exit_check_1230.dbn.zst",
      "input_rows": 79300,
      "output_rows": 2880,
      "skipped_invalid_quote": 0,
      "skipped_non_0dte": 76420,
      "trade_date": "2023-07-28"
    },
    {
      "file": "data\\raw\\spy_0dte\\databento\\insample_2023_07\\insample_2023_07\\2023-07-28_exit_check_1300.dbn.zst",
      "input_rows": 79300,
      "output_rows": 2880,
      "skipped_invalid_quote": 0,
      "skipped_non_0dte": 76420,
      "trade_date": "2023-07-28"
    },
    {
      "file": "data\\raw\\spy_0dte\\databento\\insample_2023_07\\insample_2023_07\\2023-07-28_exit_check_1330.dbn.zst",
      "input_rows": 79300,
      "output_rows": 2880,
      "skipped_invalid_quote": 0,
      "skipped_non_0dte": 76420,
      "trade_date": "2023-07-28"
    },
    {
      "file": "data\\raw\\spy_0dte\\databento\\insample_2023_07\\insample_2023_07\\2023-07-28_exit_check_1400.dbn.zst",
      "input_rows": 79300,
      "output_rows": 2880,
      "skipped_invalid_quote": 0,
      "skipped_non_0dte": 76420,
      "trade_date": "2023-07-28"
    },
    {
      "file": "data\\raw\\spy_0dte\\databento\\insample_2023_07\\insample_2023_07\\2023-07-28_exit_check_1430.dbn.zst",
      "input_rows": 79300,
      "output_rows": 2880,
      "skipped_invalid_quote": 0,
      "skipped_non_0dte": 76420,
      "trade_date": "2023-07-28"
    },
    {
      "file": "data\\raw\\spy_0dte\\databento\\insample_2023_07\\insample_2023_07\\2023-07-28_exit_check_1500.dbn.zst",
      "input_rows": 79300,
      "output_rows": 2880,
      "skipped_invalid_quote": 0,
      "skipped_non_0dte": 76420,
      "trade_date": "2023-07-28"
    },
    {
      "file": "data\\raw\\spy_0dte\\databento\\insample_2023_07\\insample_2023_07\\2023-07-28_exit_check_1530.dbn.zst",
      "input_rows": 79300,
      "output_rows": 2880,
      "skipped_invalid_quote": 0,
      "skipped_non_0dte": 76420,
      "trade_date": "2023-07-28"
    },
    {
      "file": "data\\raw\\spy_0dte\\databento\\insample_2023_07\\insample_2023_07\\2023-07-28_forced_close_1545.dbn.zst",
      "input_rows": 79300,
      "output_rows": 2880,
      "skipped_invalid_quote": 0,
      "skipped_non_0dte": 76420,
      "trade_date": "2023-07-28"
    },
    {
      "file": "data\\raw\\spy_0dte\\databento\\insample_2023_07\\insample_2023_07\\2023-07-31_entry_a_0935.dbn.zst",
      "input_rows": 69372,
      "output_rows": 2250,
      "skipped_invalid_quote": 0,
      "skipped_non_0dte": 67122,
      "trade_date": "2023-07-31"
    },
    {
      "file": "data\\raw\\spy_0dte\\databento\\insample_2023_07\\insample_2023_07\\2023-07-31_entry_b_1000.dbn.zst",
      "input_rows": 77080,
      "output_rows": 2500,
      "skipped_invalid_quote": 0,
      "skipped_non_0dte": 74580,
      "trade_date": "2023-07-31"
    },
    {
      "file": "data\\raw\\spy_0dte\\databento\\insample_2023_07\\insample_2023_07\\2023-07-31_exit_check_1030.dbn.zst",
      "input_rows": 77080,
      "output_rows": 2500,
      "skipped_invalid_quote": 0,
      "skipped_non_0dte": 74580,
      "trade_date": "2023-07-31"
    },
    {
      "file": "data\\raw\\spy_0dte\\databento\\insample_2023_07\\insample_2023_07\\2023-07-31_exit_check_1100.dbn.zst",
      "input_rows": 77080,
      "output_rows": 2500,
      "skipped_invalid_quote": 0,
      "skipped_non_0dte": 74580,
      "trade_date": "2023-07-31"
    },
    {
      "file": "data\\raw\\spy_0dte\\databento\\insample_2023_07\\insample_2023_07\\2023-07-31_exit_check_1130.dbn.zst",
      "input_rows": 77080,
      "output_rows": 2500,
      "skipped_invalid_quote": 0,
      "skipped_non_0dte": 74580,
      "trade_date": "2023-07-31"
    },
    {
      "file": "data\\raw\\spy_0dte\\databento\\insample_2023_07\\insample_2023_07\\2023-07-31_exit_check_1200.dbn.zst",
      "input_rows": 77080,
      "output_rows": 2500,
      "skipped_invalid_quote": 0,
      "skipped_non_0dte": 74580,
      "trade_date": "2023-07-31"
    },
    {
      "file": "data\\raw\\spy_0dte\\databento\\insample_2023_07\\insample_2023_07\\2023-07-31_exit_check_1230.dbn.zst",
      "input_rows": 77080,
      "output_rows": 2500,
      "skipped_invalid_quote": 0,
      "skipped_non_0dte": 74580,
      "trade_date": "2023-07-31"
    },
    {
      "file": "data\\raw\\spy_0dte\\databento\\insample_2023_07\\insample_2023_07\\2023-07-31_exit_check_1300.dbn.zst",
      "input_rows": 77080,
      "output_rows": 2500,
      "skipped_invalid_quote": 0,
      "skipped_non_0dte": 74580,
      "trade_date": "2023-07-31"
    },
    {
      "file": "data\\raw\\spy_0dte\\databento\\insample_2023_07\\insample_2023_07\\2023-07-31_exit_check_1330.dbn.zst",
      "input_rows": 77080,
      "output_rows": 2500,
      "skipped_invalid_quote": 0,
      "skipped_non_0dte": 74580,
      "trade_date": "2023-07-31"
    },
    {
      "file": "data\\raw\\spy_0dte\\databento\\insample_2023_07\\insample_2023_07\\2023-07-31_exit_check_1400.dbn.zst",
      "input_rows": 77080,
      "output_rows": 2500,
      "skipped_invalid_quote": 0,
      "skipped_non_0dte": 74580,
      "trade_date": "2023-07-31"
    },
    {
      "file": "data\\raw\\spy_0dte\\databento\\insample_2023_07\\insample_2023_07\\2023-07-31_exit_check_1430.dbn.zst",
      "input_rows": 77080,
      "output_rows": 2500,
      "skipped_invalid_quote": 0,
      "skipped_non_0dte": 74580,
      "trade_date": "2023-07-31"
    },
    {
      "file": "data\\raw\\spy_0dte\\databento\\insample_2023_07\\insample_2023_07\\2023-07-31_exit_check_1500.dbn.zst",
      "input_rows": 77080,
      "output_rows": 2500,
      "skipped_invalid_quote": 0,
      "skipped_non_0dte": 74580,
      "trade_date": "2023-07-31"
    },
    {
      "file": "data\\raw\\spy_0dte\\databento\\insample_2023_07\\insample_2023_07\\2023-07-31_exit_check_1530.dbn.zst",
      "input_rows": 77080,
      "output_rows": 2500,
      "skipped_invalid_quote": 0,
      "skipped_non_0dte": 74580,
      "trade_date": "2023-07-31"
    },
    {
      "file": "data\\raw\\spy_0dte\\databento\\insample_2023_07\\insample_2023_07\\2023-07-31_forced_close_1545.dbn.zst",
      "input_rows": 77080,
      "output_rows": 2500,
      "skipped_invalid_quote": 0,
      "skipped_non_0dte": 74580,
      "trade_date": "2023-07-31"
    }
  ],
  "input_rows": 21275056,
  "manifest": {
    "coverage_end": "2023-07-31",
    "coverage_start": "2023-07-03",
    "dataset_id": "databento-one-month-pilot-e21fab5dd67b",
    "ingested_at_et": "2026-06-30T04:16:35-04:00",
    "license_notes": "Databento OPRA.PILLAR cbbo-1m local cache. User-approved one-month pilot download.",
    "provider": "Databento",
    "raw_sha256": "e21fab5dd67bfe638df457c611c37bcc0cac018928bc82f263b92e8ed4b06df6",
    "record_type": "data_registry_manifest",
    "schema_name": "m2_contracts",
    "schema_version": "m2.0",
    "schema_version_applied": "m2.0",
    "source_url": "data\\raw\\spy_0dte\\databento\\insample_2023_07\\insample_2023_07"
  },
  "output_path": "data\\normalized\\spy_0dte\\databento\\insample_2023_07\\option_quote.jsonl",
  "output_rows": 748141,
  "provider": "Databento",
  "raw_root": "data\\raw\\spy_0dte\\databento\\insample_2023_07\\insample_2023_07",
  "registry_path": "D:\\Fogust\\Workspace\\Investment\\Project\\SPY 0DTE - Higanbana\\data\\registry\\datasets.jsonl",
  "skipped_invalid_quote": 121,
  "skipped_non_0dte": 20526794
}